<?xml version='1.0' encoding='utf-8'?>
<tv date="20250717221857 +0800" generator-info-name="epg.pw" generator-info-url="https://epg.pw/channels/105808/20250717.html" source-info-name="FREE EPG" source-info-url="https://epg.pw/api/epg.xml?channel_id=105808&amp;date=20250717&amp;timezone=None">
  <channel id="105808">
    <display-name lang="Australia">Judge Judy</display-name>
    <icon src="https://epg.pw/media/images/epg/2024/06/09/20240609083846800793_24.png" />
  </channel>
  <programme channel="mjh-10-judge-judy" start="20250717000900 +0000" stop="20250717003700 +0000">
    <title lang="zh">Judge Judy</title>
    <sub-title>Dog bite. - S3 Ep. 107</sub-title><category lang="en">Reality</category><category lang="en">Court</category><date>1999-01-26</date><icon src="https://10play.com.au/ip/s3/2022/09/02/461008ac0d02137f713ec0e4883be6c4-1177265.png" /></programme>
  <programme channel="mjh-10-judge-judy" start="20250717003700 +0000" stop="20250717010500 +0000">
    <title lang="zh">Judge Judy</title>
    <sub-title>Unpaid loans. - S3 Ep. 108</sub-title><category lang="en">Reality</category><category lang="en">Court</category><date>1999-01-27</date><icon src="https://10play.com.au/ip/s3/2022/09/02/461008ac0d02137f713ec0e4883be6c4-1177265.png" /></programme>
  <programme channel="mjh-10-judge-judy" start="20250717010500 +0000" stop="20250717013300 +0000">
    <title lang="zh">Judge Judy</title>
    <sub-title>Unpaid bills; man sues former lover for his personal possessions. - S3 Ep. 109</sub-title><category lang="en">Reality</category><category lang="en">Court</category><date>1999-01-28</date><icon src="https://10play.com.au/ip/s3/2022/09/02/461008ac0d02137f713ec0e4883be6c4-1177265.png" /></programme>
  <programme channel="mjh-10-judge-judy" start="20250717013300 +0000" stop="20250717020100 +0000">
    <title lang="zh">Judge Judy</title>
    <sub-title>Divorcees. - S3 Ep. 110</sub-title><category lang="en">Reality</category><category lang="en">Court</category><date>1999-01-29</date><icon src="https://10play.com.au/ip/s3/2022/09/02/461008ac0d02137f713ec0e4883be6c4-1177265.png" /></programme>
  <programme channel="mjh-10-judge-judy" start="20250717020100 +0000" stop="20250717022900 +0000">
    <title lang="zh">Judge Judy</title>
    <sub-title>Newlyweds sue hostel; unpaid bills. - S3 Ep. 112</sub-title><category lang="en">Reality</category><category lang="en">Court</category><date>1999-02-02</date><icon src="https://10play.com.au/ip/s3/2022/09/02/461008ac0d02137f713ec0e4883be6c4-1177265.png" /></programme>
  <programme channel="mjh-10-judge-judy" start="20250717022900 +0000" stop="20250717025700 +0000">
    <title lang="zh">Judge Judy</title>
    <sub-title>Pet snake; lost ring. - S3 Ep. 113</sub-title><category lang="en">Reality</category><category lang="en">Court</category><date>1999-02-03</date><icon src="https://10play.com.au/ip/s3/2022/09/02/461008ac0d02137f713ec0e4883be6c4-1177265.png" /></programme>
  <programme channel="mjh-10-judge-judy" start="20250717025700 +0000" stop="20250717032500 +0000">
    <title lang="zh">Judge Judy</title>
    <sub-title>Altercation; pet peacocks. - S3 Ep. 114</sub-title><category lang="en">Reality</category><category lang="en">Court</category><date>1999-02-04</date><icon src="https://10play.com.au/ip/s3/2022/09/02/461008ac0d02137f713ec0e4883be6c4-1177265.png" /></programme>
  <programme channel="mjh-10-judge-judy" start="20250717032500 +0000" stop="20250717035300 +0000">
    <title lang="zh">Judge Judy</title>
    <sub-title>Bar assault. - S3 Ep. 115</sub-title><category lang="en">Reality</category><category lang="en">Court</category><date>1999-02-05</date><icon src="https://10play.com.au/ip/s3/2022/09/02/461008ac0d02137f713ec0e4883be6c4-1177265.png" /></programme>
  <programme channel="mjh-10-judge-judy" start="20250717035300 +0000" stop="20250717042100 +0000">
    <title lang="zh">Judge Judy</title>
    <sub-title>Car loan. - S3 Ep. 117</sub-title><category lang="en">Reality</category><category lang="en">Court</category><date>1999-02-09</date><icon src="https://10play.com.au/ip/s3/2022/09/02/461008ac0d02137f713ec0e4883be6c4-1177265.png" /></programme>
  <programme channel="mjh-10-judge-judy" start="20250717042100 +0000" stop="20250717044900 +0000">
    <title lang="zh">Judge Judy</title>
    <sub-title>Vandalized car; landlord's error. - S3 Ep. 118</sub-title><category lang="en">Reality</category><category lang="en">Court</category><date>1999-02-10</date><icon src="https://10play.com.au/ip/s3/2022/09/02/461008ac0d02137f713ec0e4883be6c4-1177265.png" /></programme>
  <programme channel="mjh-10-judge-judy" start="20250717044900 +0000" stop="20250717051700 +0000">
    <title lang="zh">Judge Judy</title>
    <sub-title>Unpaid child-care bills. - S3 Ep. 119</sub-title><category lang="en">Reality</category><category lang="en">Court</category><date>1999-02-11</date><icon src="https://10play.com.au/ip/s3/2022/09/02/461008ac0d02137f713ec0e4883be6c4-1177265.png" /></programme>
  <programme channel="mjh-10-judge-judy" start="20250717051700 +0000" stop="20250717054500 +0000">
    <title lang="zh">Judge Judy</title>
    <sub-title>Son ruins a car; scratched car. - S3 Ep. 120</sub-title><category lang="en">Reality</category><category lang="en">Court</category><date>1999-02-12</date><icon src="https://10play.com.au/ip/s3/2022/09/02/461008ac0d02137f713ec0e4883be6c4-1177265.png" /></programme>
  <programme channel="mjh-10-judge-judy" start="20250717054500 +0000" stop="20250717061300 +0000">
    <title lang="zh">Judge Judy</title>
    <sub-title>Female impersonator demands payment for services; man sues a woman who claims he is stalking her. - S3 Ep. 121</sub-title><category lang="en">Reality</category><category lang="en">Court</category><date>1999-02-15</date><icon src="https://10play.com.au/ip/s3/2022/09/02/461008ac0d02137f713ec0e4883be6c4-1177265.png" /></programme>
  <programme channel="mjh-10-judge-judy" start="20250717061300 +0000" stop="20250717064100 +0000">
    <title lang="zh">Judge Judy</title>
    <sub-title>Traffic altercation. - S3 Ep. 122</sub-title><category lang="en">Reality</category><category lang="en">Court</category><date>1999-02-16</date><icon src="https://10play.com.au/ip/s3/2022/09/02/461008ac0d02137f713ec0e4883be6c4-1177265.png" /></programme>
  <programme channel="mjh-10-judge-judy" start="20250717064100 +0000" stop="20250717070800 +0000">
    <title lang="zh">Judge Judy</title>
    <sub-title>Off-duty policewoman's car is damaged. - S3 Ep. 123</sub-title><category lang="en">Reality</category><category lang="en">Court</category><date>1999-02-17</date><icon src="https://10play.com.au/ip/s3/2022/09/02/461008ac0d02137f713ec0e4883be6c4-1177265.png" /></programme>
  <programme channel="mjh-10-judge-judy" start="20250717070800 +0000" stop="20250717073600 +0000">
    <title lang="zh">Judge Judy</title>
    <sub-title>Estate dispute; parents argue over a fire started by their children. - S3 Ep. 124</sub-title><category lang="en">Reality</category><category lang="en">Court</category><date>1999-02-18</date><icon src="https://10play.com.au/ip/s3/2022/09/02/461008ac0d02137f713ec0e4883be6c4-1177265.png" /></programme>
  <programme channel="mjh-10-judge-judy" start="20250717073600 +0000" stop="20250717080400 +0000">
    <title lang="zh">Judge Judy</title>
    <sub-title>A woman's windows are smashed by her daughter's enemy. - S3 Ep. 125</sub-title><category lang="en">Reality</category><category lang="en">Court</category><date>1999-02-19</date><icon src="https://10play.com.au/ip/s3/2022/09/02/461008ac0d02137f713ec0e4883be6c4-1177265.png" /></programme>
  <programme channel="mjh-10-judge-judy" start="20250717080400 +0000" stop="20250717083200 +0000">
    <title lang="zh">Judge Judy</title>
    <sub-title>Sexual harassment. - S3 Ep. 126</sub-title><category lang="en">Reality</category><category lang="en">Court</category><date>1999-02-22</date><icon src="https://10play.com.au/ip/s3/2022/09/02/461008ac0d02137f713ec0e4883be6c4-1177265.png" /></programme>
  <programme channel="mjh-10-judge-judy" start="20250717083200 +0000" stop="20250717090000 +0000">
    <title lang="zh">Judge Judy</title>
    <sub-title>False charges. - S3 Ep. 127</sub-title><category lang="en">Reality</category><category lang="en">Court</category><date>1999-02-23</date><icon src="https://10play.com.au/ip/s3/2022/09/02/461008ac0d02137f713ec0e4883be6c4-1177265.png" /></programme>
  <programme channel="mjh-10-judge-judy" start="20250717090000 +0000" stop="20250717092800 +0000">
    <title lang="zh">Judge Judy</title>
    <sub-title>Unpaid loans; paternity. - S3 Ep. 128</sub-title><category lang="en">Reality</category><category lang="en">Court</category><date>1999-02-24</date><icon src="https://10play.com.au/ip/s3/2022/09/02/461008ac0d02137f713ec0e4883be6c4-1177265.png" /></programme>
  <programme channel="mjh-10-judge-judy" start="20250717092800 +0000" stop="20250717095600 +0000">
    <title lang="zh">Judge Judy</title>
    <sub-title>Paternity; real-estate scam. - S3 Ep. 129</sub-title><category lang="en">Reality</category><category lang="en">Court</category><date>1999-02-25</date><icon src="https://10play.com.au/ip/s3/2022/09/02/461008ac0d02137f713ec0e4883be6c4-1177265.png" /></programme>
  <programme channel="mjh-10-judge-judy" start="20250717095600 +0000" stop="20250717102400 +0000">
    <title lang="zh">Judge Judy</title>
    <sub-title>Motorcycle ownership; unpaid loans. - S3 Ep. 130</sub-title><category lang="en">Reality</category><category lang="en">Court</category><date>1999-02-26</date><icon src="https://10play.com.au/ip/s3/2022/09/02/461008ac0d02137f713ec0e4883be6c4-1177265.png" /></programme>
  <programme channel="mjh-10-judge-judy" start="20250717102400 +0000" stop="20250717105200 +0000">
    <title lang="zh">Judge Judy</title>
    <sub-title>Wedding dress; personal loan. - S3 Ep. 131</sub-title><category lang="en">Reality</category><category lang="en">Court</category><date>1999-03-01</date><icon src="https://10play.com.au/ip/s3/2022/09/02/461008ac0d02137f713ec0e4883be6c4-1177265.png" /></programme>
  <programme channel="mjh-10-judge-judy" start="20250717105200 +0000" stop="20250717112000 +0000">
    <title lang="zh">Judge Judy</title>
    <sub-title>Damaged car; bicycling boy hit. - S3 Ep. 132</sub-title><category lang="en">Reality</category><category lang="en">Court</category><date>1999-03-02</date><icon src="https://10play.com.au/ip/s3/2022/09/02/461008ac0d02137f713ec0e4883be6c4-1177265.png" /></programme>
  <programme channel="mjh-10-judge-judy" start="20250717112000 +0000" stop="20250717114800 +0000">
    <title lang="zh">Judge Judy</title>
    <sub-title>Divorcees; wrecked Jeep. - S3 Ep. 133</sub-title><category lang="en">Reality</category><category lang="en">Court</category><date>1999-03-03</date><icon src="https://10play.com.au/ip/s3/2022/09/02/461008ac0d02137f713ec0e4883be6c4-1177265.png" /></programme>
  <programme channel="mjh-10-judge-judy" start="20250717114800 +0000" stop="20250717121600 +0000">
    <title lang="zh">Judge Judy</title>
    <sub-title>Motorcycle ownership. - S3 Ep. 134</sub-title><category lang="en">Reality</category><category lang="en">Court</category><date>1999-03-04</date><icon src="https://10play.com.au/ip/s3/2022/09/02/461008ac0d02137f713ec0e4883be6c4-1177265.png" /></programme>
  <programme channel="mjh-10-judge-judy" start="20250717121600 +0000" stop="20250717124400 +0000">
    <title lang="zh">Judge Judy</title>
    <sub-title>Divorcees battle over their daughter's expenses. - S3 Ep. 135</sub-title><category lang="en">Reality</category><category lang="en">Court</category><date>1999-03-05</date><icon src="https://10play.com.au/ip/s3/2022/09/02/461008ac0d02137f713ec0e4883be6c4-1177265.png" /></programme>
  <programme channel="mjh-10-judge-judy" start="20250717124400 +0000" stop="20250717131200 +0000">
    <title lang="zh">Judge Judy</title>
    <sub-title>Unpaid loans. - S3 Ep. 136</sub-title><category lang="en">Reality</category><category lang="en">Court</category><date>1999-03-08</date><icon src="https://10play.com.au/ip/s3/2022/09/02/461008ac0d02137f713ec0e4883be6c4-1177265.png" /></programme>
  <programme channel="mjh-10-judge-judy" start="20250717131200 +0000" stop="20250717134000 +0000">
    <title lang="zh">Judge Judy</title>
    <sub-title>Child-care costs; driver sues passenger. - S3 Ep. 137</sub-title><category lang="en">Reality</category><category lang="en">Court</category><date>1999-03-09</date><icon src="https://10play.com.au/ip/s3/2022/09/02/461008ac0d02137f713ec0e4883be6c4-1177265.png" /></programme>
  <programme channel="mjh-10-judge-judy" start="20250717134000 +0000" stop="20250717140800 +0000">
    <title lang="zh">Judge Judy</title>
    <sub-title>Child support. - S3 Ep. 138</sub-title><category lang="en">Reality</category><category lang="en">Court</category><date>1999-03-10</date><icon src="https://10play.com.au/ip/s3/2022/09/02/461008ac0d02137f713ec0e4883be6c4-1177265.png" /></programme>
  <programme channel="mjh-10-judge-judy" start="20250717140800 +0000" stop="20250717143600 +0000">
    <title lang="zh">Judge Judy</title>
    <sub-title>Woman sues disabled former husband; lost gold necklace. - S3 Ep. 139</sub-title><category lang="en">Reality</category><category lang="en">Court</category><date>1999-03-11</date><icon src="https://10play.com.au/ip/s3/2022/09/02/461008ac0d02137f713ec0e4883be6c4-1177265.png" /></programme>
  <programme channel="mjh-10-judge-judy" start="20250717143600 +0000" stop="20250717150400 +0000">
    <title lang="zh">Judge Judy</title>
    <sub-title>Damaged door; borrowed money. - S3 Ep. 140</sub-title><category lang="en">Reality</category><category lang="en">Court</category><date>1999-03-12</date><icon src="https://10play.com.au/ip/s3/2022/09/02/461008ac0d02137f713ec0e4883be6c4-1177265.png" /></programme>
  <programme channel="mjh-10-judge-judy" start="20250717150400 +0000" stop="20250717153200 +0000">
    <title lang="zh">Judge Judy</title>
    <sub-title>Evicted musicians; credit-card bills. - S3 Ep. 141</sub-title><category lang="en">Reality</category><category lang="en">Court</category><date>1999-03-15</date><icon src="https://10play.com.au/ip/s3/2022/09/02/461008ac0d02137f713ec0e4883be6c4-1177265.png" /></programme>
  <programme channel="mjh-10-judge-judy" start="20250717153200 +0000" stop="20250717160000 +0000">
    <title lang="zh">Judge Judy</title>
    <sub-title>Damaged car; unfriendly neighbors. - S3 Ep. 142</sub-title><category lang="en">Reality</category><category lang="en">Court</category><date>1999-03-16</date><icon src="https://10play.com.au/ip/s3/2022/09/02/461008ac0d02137f713ec0e4883be6c4-1177265.png" /></programme>
  <programme channel="mjh-10-judge-judy" start="20250717160000 +0000" stop="20250717162800 +0000">
    <title lang="zh">Judge Judy</title>
    <sub-title>Couples' quarrels. - S3 Ep. 143</sub-title><category lang="en">Reality</category><category lang="en">Court</category><date>1999-03-17</date><icon src="https://10play.com.au/ip/s3/2022/09/02/461008ac0d02137f713ec0e4883be6c4-1177265.png" /></programme>
  <programme channel="mjh-10-judge-judy" start="20250717162800 +0000" stop="20250717165600 +0000">
    <title lang="zh">Judge Judy</title>
    <sub-title>Damaged door; unpaid loan. - S3 Ep. 144</sub-title><category lang="en">Reality</category><category lang="en">Court</category><date>1999-03-18</date><icon src="https://10play.com.au/ip/s3/2022/09/02/461008ac0d02137f713ec0e4883be6c4-1177265.png" /></programme>
  <programme channel="mjh-10-judge-judy" start="20250717165600 +0000" stop="20250717172400 +0000">
    <title lang="zh">Judge Judy</title>
    <sub-title>Rent money; assault. - S3 Ep. 145</sub-title><category lang="en">Reality</category><category lang="en">Court</category><date>1999-03-19</date><icon src="https://10play.com.au/ip/s3/2022/09/02/461008ac0d02137f713ec0e4883be6c4-1177265.png" /></programme>
  <programme channel="mjh-10-judge-judy" start="20250717172400 +0000" stop="20250717175200 +0000">
    <title lang="zh">Judge Judy</title>
    <sub-title>Bitter breakup; karaoke machine. - S3 Ep. 146</sub-title><category lang="en">Reality</category><category lang="en">Court</category><date>1999-03-22</date><icon src="https://10play.com.au/ip/s3/2022/09/02/461008ac0d02137f713ec0e4883be6c4-1177265.png" /></programme>
  <programme channel="mjh-10-judge-judy" start="20250717175200 +0000" stop="20250717182000 +0000">
    <title lang="zh">Judge Judy</title>
    <sub-title>Wedding photographer; bail loan. - S3 Ep. 147</sub-title><category lang="en">Reality</category><category lang="en">Court</category><date>1999-03-23</date><icon src="https://10play.com.au/ip/s3/2022/09/02/461008ac0d02137f713ec0e4883be6c4-1177265.png" /></programme>
  <programme channel="mjh-10-judge-judy" start="20250717182000 +0000" stop="20250717184800 +0000">
    <title lang="zh">Judge Judy</title>
    <sub-title>Abusive spouse. - S3 Ep. 148</sub-title><category lang="en">Reality</category><category lang="en">Court</category><date>1999-03-24</date><icon src="https://10play.com.au/ip/s3/2022/09/02/461008ac0d02137f713ec0e4883be6c4-1177265.png" /></programme>
  <programme channel="mjh-10-judge-judy" start="20250717184800 +0000" stop="20250717191600 +0000">
    <title lang="zh">Judge Judy</title>
    <sub-title>Divorced couple quarrel over money. - S3 Ep. 150</sub-title><category lang="en">Reality</category><category lang="en">Court</category><date>1999-03-26</date><icon src="https://10play.com.au/ip/s3/2022/09/02/461008ac0d02137f713ec0e4883be6c4-1177265.png" /></programme>
  <programme channel="mjh-10-judge-judy" start="20250717191600 +0000" stop="20250717194400 +0000">
    <title lang="zh">Judge Judy</title>
    <sub-title>Parking-lot altercation; a dead parakeet. - S3 Ep. 151</sub-title><category lang="en">Reality</category><category lang="en">Court</category><date>1999-03-29</date><icon src="https://10play.com.au/ip/s3/2022/09/02/461008ac0d02137f713ec0e4883be6c4-1177265.png" /></programme>
  <programme channel="mjh-10-judge-judy" start="20250717194400 +0000" stop="20250717201200 +0000">
    <title lang="zh">Judge Judy</title>
    <sub-title>Former couples battle over unpaid bills. - S3 Ep. 152</sub-title><category lang="en">Reality</category><category lang="en">Court</category><date>1999-03-30</date><icon src="https://10play.com.au/ip/s3/2022/09/02/461008ac0d02137f713ec0e4883be6c4-1177265.png" /></programme>
  <programme channel="mjh-10-judge-judy" start="20250717201200 +0000" stop="20250717204000 +0000">
    <title lang="zh">Judge Judy</title>
    <sub-title>Credit cards and harassment; woman fights ex for child support. - S3 Ep. 153</sub-title><category lang="en">Reality</category><category lang="en">Court</category><date>1999-03-31</date><icon src="https://10play.com.au/ip/s3/2022/09/02/461008ac0d02137f713ec0e4883be6c4-1177265.png" /></programme>
  <programme channel="mjh-10-judge-judy" start="20250717204000 +0000" stop="20250717210800 +0000">
    <title lang="zh">Judge Judy</title>
    <sub-title>Woman sues ex-husband; alleged gifts. - S3 Ep. 154</sub-title><category lang="en">Reality</category><category lang="en">Court</category><date>1999-04-01</date><icon src="https://10play.com.au/ip/s3/2022/09/02/461008ac0d02137f713ec0e4883be6c4-1177265.png" /></programme>
  <programme channel="mjh-10-judge-judy" start="20250717210800 +0000" stop="20250717213600 +0000">
    <title lang="zh">Judge Judy</title>
    <sub-title>Musicians are evicted; credit-card dispute. - S3 Ep. 155</sub-title><category lang="en">Reality</category><category lang="en">Court</category><date>1999-04-02</date><icon src="https://10play.com.au/ip/s3/2022/09/02/461008ac0d02137f713ec0e4883be6c4-1177265.png" /></programme>
  <programme channel="mjh-10-judge-judy" start="20250717213600 +0000" stop="20250717220400 +0000">
    <title lang="zh">Judge Judy</title>
    <sub-title>Body builder alleges harassment. - S3 Ep. 156</sub-title><category lang="en">Reality</category><category lang="en">Court</category><date>1999-04-05</date><icon src="https://10play.com.au/ip/s3/2022/09/02/461008ac0d02137f713ec0e4883be6c4-1177265.png" /></programme>
  <programme channel="mjh-10-judge-judy" start="20250717220400 +0000" stop="20250717223200 +0000">
    <title lang="zh">Judge Judy</title>
    <sub-title>Vacuum cleaner; freeloading friend. - S3 Ep. 157</sub-title><category lang="en">Reality</category><category lang="en">Court</category><date>1999-04-06</date><icon src="https://10play.com.au/ip/s3/2022/09/02/461008ac0d02137f713ec0e4883be6c4-1177265.png" /></programme>
  <programme channel="mjh-10-judge-judy" start="20250717223200 +0000" stop="20250717230000 +0000">
    <title lang="zh">Judge Judy</title>
    <sub-title>Parents sue daughter; unpaid loan. - S3 Ep. 158</sub-title><category lang="en">Reality</category><category lang="en">Court</category><date>1999-04-07</date><icon src="https://10play.com.au/ip/s3/2022/09/02/461008ac0d02137f713ec0e4883be6c4-1177265.png" /></programme>
  <programme channel="mjh-10-judge-judy" start="20250717230000 +0000" stop="20250717232800 +0000">
    <title lang="zh">Judge Judy</title>
    <sub-title>Impounded car; former lovers. - S3 Ep. 159</sub-title><category lang="en">Reality</category><category lang="en">Court</category><date>1999-04-08</date><icon src="https://10play.com.au/ip/s3/2022/09/02/461008ac0d02137f713ec0e4883be6c4-1177265.png" /></programme>
  <programme channel="mjh-10-judge-judy" start="20250717232800 +0000" stop="20250717235500 +0000">
    <title lang="zh">Judge Judy</title>
    <sub-title>Day-care dispute; jazz-festival tickets. - S3 Ep. 160</sub-title><category lang="en">Reality</category><category lang="en">Court</category><date>1999-04-09</date><icon src="https://10play.com.au/ip/s3/2022/09/02/461008ac0d02137f713ec0e4883be6c4-1177265.png" /></programme>
  <programme channel="mjh-10-judge-judy" start="20250717235500 +0000" stop="20250718000000 +0000">
    <title lang="zh">Judge Judy</title>
    <sub-title>Road rage; repossessed vehicles. - S3 Ep. 161</sub-title><category lang="en">Reality</category><category lang="en">Court</category><date>1999-04-12</date><icon src="https://10play.com.au/ip/s3/2022/09/02/461008ac0d02137f713ec0e4883be6c4-1177265.png" /></programme>
  <programme channel="mjh-10-judge-judy" start="20250718002300 +0000" stop="20250718005100 +0000">
    <title lang="zh">Judge Judy</title>
    <sub-title>Property dispute; exotic dancers. - S3 Ep. 162</sub-title><category lang="en">Reality</category><category lang="en">Court</category><date>1999-04-13</date><icon src="https://10play.com.au/ip/s3/2022/09/02/461008ac0d02137f713ec0e4883be6c4-1177265.png" /></programme>
  <programme channel="mjh-10-judge-judy" start="20250718005100 +0000" stop="20250718011900 +0000">
    <title lang="zh">Judge Judy</title>
    <sub-title>Car loan; credit problems. - S3 Ep. 163</sub-title><category lang="en">Reality</category><category lang="en">Court</category><date>1999-04-14</date><icon src="https://10play.com.au/ip/s3/2022/09/02/461008ac0d02137f713ec0e4883be6c4-1177265.png" /></programme>
  <programme channel="mjh-10-judge-judy" start="20250718011900 +0000" stop="20250718014700 +0000">
    <title lang="zh">Judge Judy</title>
    <sub-title>Love triangle; bank-account access. - S3 Ep. 164</sub-title><category lang="en">Reality</category><category lang="en">Court</category><date>1999-04-15</date><icon src="https://10play.com.au/ip/s3/2022/09/02/461008ac0d02137f713ec0e4883be6c4-1177265.png" /></programme>
  <programme channel="mjh-10-judge-judy" start="20250718014700 +0000" stop="20250718021500 +0000">
    <title lang="zh">Judge Judy</title>
    <sub-title>Phone sex; former roommates. - S3 Ep. 165</sub-title><category lang="en">Reality</category><category lang="en">Court</category><date>1999-04-16</date><icon src="https://10play.com.au/ip/s3/2022/09/02/461008ac0d02137f713ec0e4883be6c4-1177265.png" /></programme>
  <programme channel="mjh-10-judge-judy" start="20250718021500 +0000" stop="20250718024300 +0000">
    <title lang="zh">Judge Judy</title>
    <sub-title>Former couple's possessions; child support. - S3 Ep. 166</sub-title><category lang="en">Reality</category><category lang="en">Court</category><date>1999-04-19</date><icon src="https://10play.com.au/ip/s3/2022/09/02/461008ac0d02137f713ec0e4883be6c4-1177265.png" /></programme>
  <programme channel="mjh-10-judge-judy" start="20250718024300 +0000" stop="20250718031100 +0000">
    <title lang="zh">Judge Judy</title>
    <sub-title>Assault; engagement ring. - S3 Ep. 167</sub-title><category lang="en">Reality</category><category lang="en">Court</category><date>1999-04-20</date><icon src="https://10play.com.au/ip/s3/2022/09/02/461008ac0d02137f713ec0e4883be6c4-1177265.png" /></programme>
  <programme channel="mjh-10-judge-judy" start="20250718031100 +0000" stop="20250718033900 +0000">
    <title lang="zh">Judge Judy</title>
    <sub-title>Unpaid loan; man requests that his late father's possessions be returned. - S3 Ep. 168</sub-title><category lang="en">Reality</category><category lang="en">Court</category><date>1999-04-21</date><icon src="https://10play.com.au/ip/s3/2022/09/02/461008ac0d02137f713ec0e4883be6c4-1177265.png" /></programme>
  <programme channel="mjh-10-judge-judy" start="20250718033900 +0000" stop="20250718040700 +0000">
    <title lang="zh">Judge Judy</title>
    <sub-title>Ownership of rings; breakup. - S3 Ep. 169</sub-title><category lang="en">Reality</category><category lang="en">Court</category><date>1999-04-22</date><icon src="https://10play.com.au/ip/s3/2022/09/02/461008ac0d02137f713ec0e4883be6c4-1177265.png" /></programme>
  <programme channel="mjh-10-judge-judy" start="20250718040700 +0000" stop="20250718043500 +0000">
    <title lang="zh">Judge Judy</title>
    <sub-title>Loan repayment; divorced couple's debts. - S3 Ep. 170</sub-title><category lang="en">Reality</category><category lang="en">Court</category><date>1999-04-23</date><icon src="https://10play.com.au/ip/s3/2022/09/02/461008ac0d02137f713ec0e4883be6c4-1177265.png" /></programme>
  <programme channel="mjh-10-judge-judy" start="20250718043500 +0000" stop="20250718050300 +0000">
    <title lang="zh">Judge Judy</title>
    <sub-title>Former couple's possessions. - S3 Ep. 171</sub-title><category lang="en">Reality</category><category lang="en">Court</category><date>1999-04-26</date><icon src="https://10play.com.au/ip/s3/2022/09/02/461008ac0d02137f713ec0e4883be6c4-1177265.png" /></programme>
  <programme channel="mjh-10-judge-judy" start="20250718050300 +0000" stop="20250718053100 +0000">
    <title lang="zh">Judge Judy</title>
    <sub-title>Assault. - S3 Ep. 172</sub-title><category lang="en">Reality</category><category lang="en">Court</category><date>1999-04-27</date><icon src="https://10play.com.au/ip/s3/2022/09/02/461008ac0d02137f713ec0e4883be6c4-1177265.png" /></programme>
  <programme channel="mjh-10-judge-judy" start="20250718053100 +0000" stop="20250718055900 +0000">
    <title lang="zh">Judge Judy</title>
    <sub-title>Jealous rage. - S3 Ep. 173</sub-title><category lang="en">Reality</category><category lang="en">Court</category><date>1999-04-28</date><icon src="https://10play.com.au/ip/s3/2022/09/02/461008ac0d02137f713ec0e4883be6c4-1177265.png" /></programme>
  <programme channel="mjh-10-judge-judy" start="20250718055900 +0000" stop="20250718062700 +0000">
    <title lang="zh">Judge Judy</title>
    <sub-title>Model sues mechanic. - S3 Ep. 174</sub-title><category lang="en">Reality</category><category lang="en">Court</category><date>1999-04-29</date><icon src="https://10play.com.au/ip/s3/2022/09/02/461008ac0d02137f713ec0e4883be6c4-1177265.png" /></programme>
  <programme channel="mjh-10-judge-judy" start="20250718062700 +0000" stop="20250718065500 +0000">
    <title lang="zh">Judge Judy</title>
    <sub-title>Broken fingers; $500 loan. - S3 Ep. 175</sub-title><category lang="en">Reality</category><category lang="en">Court</category><date>1999-04-30</date><icon src="https://10play.com.au/ip/s3/2022/09/02/461008ac0d02137f713ec0e4883be6c4-1177265.png" /></programme>
  <programme channel="mjh-10-judge-judy" start="20250718065500 +0000" stop="20250718072300 +0000">
    <title lang="zh">Judge Judy</title>
    <sub-title>Woman sues former son-in-law; man hits janitor. - S3 Ep. 176</sub-title><category lang="en">Reality</category><category lang="en">Court</category><date>1999-05-03</date><icon src="https://10play.com.au/ip/s3/2022/09/02/461008ac0d02137f713ec0e4883be6c4-1177265.png" /></programme>
  <programme channel="mjh-10-judge-judy" start="20250718072300 +0000" stop="20250718075100 +0000">
    <title lang="zh">Judge Judy</title>
    <sub-title>Unpaid phone bills; phone-calling card. - S3 Ep. 177</sub-title><category lang="en">Reality</category><category lang="en">Court</category><date>1999-05-04</date><icon src="https://10play.com.au/ip/s3/2022/09/02/461008ac0d02137f713ec0e4883be6c4-1177265.png" /></programme>
  <programme channel="mjh-10-judge-judy" start="20250718075100 +0000" stop="20250718081900 +0000">
    <title lang="zh">Judge Judy</title>
    <sub-title>Breast-enlargement suit. - S3 Ep. 178</sub-title><category lang="en">Reality</category><category lang="en">Court</category><date>1999-05-05</date><icon src="https://10play.com.au/ip/s3/2022/09/02/461008ac0d02137f713ec0e4883be6c4-1177265.png" /></programme>
  <programme channel="mjh-10-judge-judy" start="20250718081900 +0000" stop="20250718084700 +0000">
    <title lang="zh">Judge Judy</title>
    <sub-title>Mother sues voice coach; emcee sues for payment. - S3 Ep. 179</sub-title><category lang="en">Reality</category><category lang="en">Court</category><date>1999-05-06</date><icon src="https://10play.com.au/ip/s3/2022/09/02/461008ac0d02137f713ec0e4883be6c4-1177265.png" /></programme>
  <programme channel="mjh-10-judge-judy" start="20250718084700 +0000" stop="20250718091500 +0000">
    <title lang="zh">Judge Judy</title>
    <sub-title>Divorcees quarrel over possessions. - S3 Ep. 180</sub-title><category lang="en">Reality</category><category lang="en">Court</category><date>1999-05-07</date><icon src="https://10play.com.au/ip/s3/2022/09/02/461008ac0d02137f713ec0e4883be6c4-1177265.png" /></programme>
  <programme channel="mjh-10-judge-judy" start="20250718091500 +0000" stop="20250718094300 +0000">
    <title lang="zh">Judge Judy</title>
    <sub-title>Mall owner sues tenant; former couple's futon. - S3 Ep. 181</sub-title><category lang="en">Reality</category><category lang="en">Court</category><date>1999-05-10</date><icon src="https://10play.com.au/ip/s3/2022/09/02/461008ac0d02137f713ec0e4883be6c4-1177265.png" /></programme>
  <programme channel="mjh-10-judge-judy" start="20250718094300 +0000" stop="20250718101100 +0000">
    <title lang="zh">Judge Judy</title>
    <sub-title>Stolen shoes; broken car-seat. - S3 Ep. 182</sub-title><category lang="en">Reality</category><category lang="en">Court</category><date>1999-05-11</date><icon src="https://10play.com.au/ip/s3/2022/09/02/461008ac0d02137f713ec0e4883be6c4-1177265.png" /></programme>
  <programme channel="mjh-10-judge-judy" start="20250718101100 +0000" stop="20250718103900 +0000">
    <title lang="zh">Judge Judy</title>
    <sub-title>Domestic abuse and damaged property. - S3 Ep. 183</sub-title><category lang="en">Reality</category><category lang="en">Court</category><date>1999-05-12</date><icon src="https://10play.com.au/ip/s3/2022/09/02/461008ac0d02137f713ec0e4883be6c4-1177265.png" /></programme>
  <programme channel="mjh-10-judge-judy" start="20250718103900 +0000" stop="20250718110700 +0000">
    <title lang="zh">Judge Judy</title>
    <sub-title>Mother sues gang-member son. - S3 Ep. 184</sub-title><category lang="en">Reality</category><category lang="en">Court</category><date>1999-05-13</date><icon src="https://10play.com.au/ip/s3/2022/09/02/461008ac0d02137f713ec0e4883be6c4-1177265.png" /></programme>
  <programme channel="mjh-10-judge-judy" start="20250718110700 +0000" stop="20250718113500 +0000">
    <title lang="zh">Judge Judy</title>
    <sub-title>Woman sues husband's lover; repossessed car. - S3 Ep. 185</sub-title><category lang="en">Reality</category><category lang="en">Court</category><date>1999-05-14</date><icon src="https://10play.com.au/ip/s3/2022/09/02/461008ac0d02137f713ec0e4883be6c4-1177265.png" /></programme>
  <programme channel="mjh-10-judge-judy" start="20250718113500 +0000" stop="20250718120300 +0000">
    <title lang="zh">Judge Judy</title>
    <sub-title>Woman sues son for visitation rights. - S3 Ep. 186</sub-title><category lang="en">Reality</category><category lang="en">Court</category><date>1999-05-17</date><icon src="https://10play.com.au/ip/s3/2022/09/02/461008ac0d02137f713ec0e4883be6c4-1177265.png" /></programme>
  <programme channel="mjh-10-judge-judy" start="20250718120300 +0000" stop="20250718123100 +0000">
    <title lang="zh">Judge Judy</title>
    <sub-title>Property damage; calling-card debt. - S3 Ep. 187</sub-title><category lang="en">Reality</category><category lang="en">Court</category><date>1999-05-18</date><icon src="https://10play.com.au/ip/s3/2022/09/02/461008ac0d02137f713ec0e4883be6c4-1177265.png" /></programme>
  <programme channel="mjh-10-judge-judy" start="20250718123100 +0000" stop="20250718125900 +0000">
    <title lang="zh">Judge Judy</title>
    <sub-title>Feuding divorcees; unpaid loan. - S3 Ep. 188</sub-title><category lang="en">Reality</category><category lang="en">Court</category><date>1999-05-19</date><icon src="https://10play.com.au/ip/s3/2022/09/02/461008ac0d02137f713ec0e4883be6c4-1177265.png" /></programme>
  <programme channel="mjh-10-judge-judy" start="20250718125900 +0000" stop="20250718132700 +0000">
    <title lang="zh">Judge Judy</title>
    <sub-title>Former lovers battle over expenses and harassment. - S3 Ep. 189</sub-title><category lang="en">Reality</category><category lang="en">Court</category><date>1999-05-20</date><icon src="https://10play.com.au/ip/s3/2022/09/02/461008ac0d02137f713ec0e4883be6c4-1177265.png" /></programme>
  <programme channel="mjh-10-judge-judy" start="20250718132700 +0000" stop="20250718135500 +0000">
    <title lang="zh">Judge Judy</title>
    <sub-title>Angry woman breaks man's camera; student sues former boyfriend. - S3 Ep. 190</sub-title><category lang="en">Reality</category><category lang="en">Court</category><date>1999-05-21</date><icon src="https://10play.com.au/ip/s3/2022/09/02/461008ac0d02137f713ec0e4883be6c4-1177265.png" /></programme>
  <programme channel="mjh-10-judge-judy" start="20250718135500 +0000" stop="20250718142300 +0000">
    <title lang="zh">Judge Judy</title>
    <sub-title>Man charges ex with theft and extortion. - S3 Ep. 191</sub-title><category lang="en">Reality</category><category lang="en">Court</category><date>1999-05-24</date><icon src="https://10play.com.au/ip/s3/2022/09/02/461008ac0d02137f713ec0e4883be6c4-1177265.png" /></programme>
  <programme channel="mjh-10-judge-judy" start="20250718142300 +0000" stop="20250718145100 +0000">
    <title lang="zh">Judge Judy</title>
    <sub-title>Negligence; unpaid debts. - S3 Ep. 192</sub-title><category lang="en">Reality</category><category lang="en">Court</category><date>1999-05-25</date><icon src="https://10play.com.au/ip/s3/2022/09/02/461008ac0d02137f713ec0e4883be6c4-1177265.png" /></programme>
  <programme channel="mjh-10-judge-judy" start="20250718145100 +0000" stop="20250718151900 +0000">
    <title lang="zh">Judge Judy</title>
    <sub-title>Former fiances battle over wedding expenses; stolen belongings. - S3 Ep. 193</sub-title><category lang="en">Reality</category><category lang="en">Court</category><date>1999-05-26</date><icon src="https://10play.com.au/ip/s3/2022/09/02/461008ac0d02137f713ec0e4883be6c4-1177265.png" /></programme>
  <programme channel="mjh-10-judge-judy" start="20250718151900 +0000" stop="20250718154700 +0000">
    <title lang="zh">Judge Judy</title>
    <sub-title>Neighbor damages man's door; unpaid loan. - S3 Ep. 194</sub-title><category lang="en">Reality</category><category lang="en">Court</category><date>1999-05-27</date><icon src="https://10play.com.au/ip/s3/2022/09/02/461008ac0d02137f713ec0e4883be6c4-1177265.png" /></programme>
  <programme channel="mjh-10-judge-judy" start="20250718154700 +0000" stop="20250718161500 +0000">
    <title lang="zh">Judge Judy</title>
    <sub-title>Bar owner demands repayment of a loan; credit-card debt. - S3 Ep. 195</sub-title><category lang="en">Reality</category><category lang="en">Court</category><date>1999-05-28</date><icon src="https://10play.com.au/ip/s3/2022/09/02/461008ac0d02137f713ec0e4883be6c4-1177265.png" /></programme>
  <programme channel="mjh-10-judge-judy" start="20250718161500 +0000" stop="20250718164200 +0000">
    <title lang="zh">Judge Judy</title>
    <sub-title>Fired clerk sues customer; former couple's property. - S3 Ep. 196</sub-title><category lang="en">Reality</category><category lang="en">Court</category><date>1999-05-31</date><icon src="https://10play.com.au/ip/s3/2022/09/02/461008ac0d02137f713ec0e4883be6c4-1177265.png" /></programme>
  <programme channel="mjh-10-judge-judy" start="20250718164200 +0000" stop="20250718171000 +0000">
    <title lang="zh">Judge Judy</title>
    <sub-title>Hair weave. - S3 Ep. 197</sub-title><category lang="en">Reality</category><category lang="en">Court</category><date>1999-06-01</date><icon src="https://10play.com.au/ip/s3/2022/09/02/461008ac0d02137f713ec0e4883be6c4-1177265.png" /></programme>
  <programme channel="mjh-10-judge-judy" start="20250718171000 +0000" stop="20250718173800 +0000">
    <title lang="zh">Judge Judy</title>
    <sub-title>Supervisor vs. former employee; former friends. - S3 Ep. 198</sub-title><category lang="en">Reality</category><category lang="en">Court</category><date>1999-06-02</date><icon src="https://10play.com.au/ip/s3/2022/09/02/461008ac0d02137f713ec0e4883be6c4-1177265.png" /></programme>
  <programme channel="mjh-10-judge-judy" start="20250718173800 +0000" stop="20250718180600 +0000">
    <title lang="zh">Judge Judy</title>
    <sub-title>Divorced couple's quarrels; inheritance quarrel. - S3 Ep. 199</sub-title><category lang="en">Reality</category><category lang="en">Court</category><date>1999-06-03</date><icon src="https://10play.com.au/ip/s3/2022/09/02/461008ac0d02137f713ec0e4883be6c4-1177265.png" /></programme>
  <programme channel="mjh-10-judge-judy" start="20250718180600 +0000" stop="20250718183400 +0000">
    <title lang="zh">Judge Judy</title>
    <sub-title>Ex-roommates sue for rent money; man shoots neighbor's dog. - S3 Ep. 200</sub-title><category lang="en">Reality</category><category lang="en">Court</category><date>1999-06-04</date><icon src="https://10play.com.au/ip/s3/2022/09/02/461008ac0d02137f713ec0e4883be6c4-1177265.png" /></programme>
  <programme channel="mjh-10-judge-judy" start="20250718183400 +0000" stop="20250718190200 +0000">
    <title lang="zh">Judge Judy</title>
    <sub-title>Back rent; teenage fist-fight. - S3 Ep. 201</sub-title><category lang="en">Reality</category><category lang="en">Court</category><date>1999-06-07</date><icon src="https://10play.com.au/ip/s3/2022/09/02/461008ac0d02137f713ec0e4883be6c4-1177265.png" /></programme>
  <programme channel="mjh-10-judge-judy" start="20250718190200 +0000" stop="20250718193000 +0000">
    <title lang="zh">Judge Judy</title>
    <sub-title>Woman sues ex-lover and his girlfriend; wrecked car. - S3 Ep. 202</sub-title><category lang="en">Reality</category><category lang="en">Court</category><date>1999-06-08</date><icon src="https://10play.com.au/ip/s3/2022/09/02/461008ac0d02137f713ec0e4883be6c4-1177265.png" /></programme>
  <programme channel="mjh-10-judge-judy" start="20250718193000 +0000" stop="20250718195800 +0000">
    <title lang="zh">Judge Judy</title>
    <sub-title>Exotic dancer's gold chain. - S3 Ep. 203</sub-title><category lang="en">Reality</category><category lang="en">Court</category><date>1999-06-09</date><icon src="https://10play.com.au/ip/s3/2022/09/02/461008ac0d02137f713ec0e4883be6c4-1177265.png" /></programme>
  <programme channel="mjh-10-judge-judy" start="20250718195800 +0000" stop="20250718202600 +0000">
    <title lang="zh">Judge Judy</title>
    <sub-title>Mothers sue over theft charges. - S3 Ep. 204</sub-title><category lang="en">Reality</category><category lang="en">Court</category><date>1999-06-10</date><icon src="https://10play.com.au/ip/s3/2022/09/02/461008ac0d02137f713ec0e4883be6c4-1177265.png" /></programme>
  <programme channel="mjh-10-judge-judy" start="20250718202600 +0000" stop="20250718205400 +0000">
    <title lang="zh">Judge Judy</title>
    <sub-title>Run off the road; dead puppy. - S3 Ep. 205</sub-title><category lang="en">Reality</category><category lang="en">Court</category><date>1999-06-11</date><icon src="https://10play.com.au/ip/s3/2022/09/02/461008ac0d02137f713ec0e4883be6c4-1177265.png" /></programme>
  <programme channel="mjh-10-judge-judy" start="20250718205400 +0000" stop="20250718212200 +0000">
    <title lang="zh">Judge Judy</title>
    <sub-title>Slashed tire; unpaid debts. - S3 Ep. 206</sub-title><category lang="en">Reality</category><category lang="en">Court</category><date>1999-06-14</date><icon src="https://10play.com.au/ip/s3/2022/09/02/461008ac0d02137f713ec0e4883be6c4-1177265.png" /></programme>
  <programme channel="mjh-10-judge-judy" start="20250718212200 +0000" stop="20250718215000 +0000">
    <title lang="zh">Judge Judy</title>
    <sub-title>Former lovers' suit. - S3 Ep. 207</sub-title><category lang="en">Reality</category><category lang="en">Court</category><date>1999-06-15</date><icon src="https://10play.com.au/ip/s3/2022/09/02/461008ac0d02137f713ec0e4883be6c4-1177265.png" /></programme>
  <programme channel="mjh-10-judge-judy" start="20250718215000 +0000" stop="20250718221800 +0000">
    <title lang="zh">Judge Judy</title>
    <sub-title>Attorney sued; damaged cars. - S3 Ep. 208</sub-title><category lang="en">Reality</category><category lang="en">Court</category><date>1999-06-16</date><icon src="https://10play.com.au/ip/s3/2022/09/02/461008ac0d02137f713ec0e4883be6c4-1177265.png" /></programme>
  <programme channel="mjh-10-judge-judy" start="20250718221800 +0000" stop="20250718224600 +0000">
    <title lang="zh">Judge Judy</title>
    <sub-title>Vindictive mother-in-law; traffic ticket. - S3 Ep. 209</sub-title><category lang="en">Reality</category><category lang="en">Court</category><date>1999-06-17</date><icon src="https://10play.com.au/ip/s3/2022/09/02/461008ac0d02137f713ec0e4883be6c4-1177265.png" /></programme>
  <programme channel="mjh-10-judge-judy" start="20250718224600 +0000" stop="20250718231400 +0000">
    <title lang="zh">Judge Judy</title>
    <sub-title>Unpaid debts; car-rental loan. - S3 Ep. 210</sub-title><category lang="en">Reality</category><category lang="en">Court</category><date>1999-06-18</date><icon src="https://10play.com.au/ip/s3/2022/09/02/461008ac0d02137f713ec0e4883be6c4-1177265.png" /></programme>
  <programme channel="mjh-10-judge-judy" start="20250718231400 +0000" stop="20250718234200 +0000">
    <title lang="zh">Judge Judy</title>
    <sub-title>Bail dispute; gold necklace. - S3 Ep. 211</sub-title><category lang="en">Reality</category><category lang="en">Court</category><date>1999-06-21</date><icon src="https://10play.com.au/ip/s3/2022/09/02/461008ac0d02137f713ec0e4883be6c4-1177265.png" /></programme>
  <programme channel="mjh-10-judge-judy" start="20250718234200 +0000" stop="20250719000000 +0000">
    <title lang="zh">Judge Judy</title>
    <sub-title>Youthful breakup; injured dog. - S3 Ep. 212</sub-title><category lang="en">Reality</category><category lang="en">Court</category><date>1999-06-22</date><icon src="https://10play.com.au/ip/s3/2022/09/02/461008ac0d02137f713ec0e4883be6c4-1177265.png" /></programme>
</tv>