<?xml version='1.0' encoding='UTF-8'?> <!DOCTYPE tv SYSTEM "xmltv.dtd">
<tv date="20250528084235 +0800" generator-info-name="epg.pw" generator-info-url="https://epg.pw/channels/403674/20250528.html" source-info-name="FREE EPG" source-info-url="https://epg.pw/api/epg.xml?channel_id=403674&amp;date=20250528&amp;timezone=None">
  <channel id="403674">
    <display-name lang="US">Disney Junior USA - East</display-name>
    <icon src="" />
  </channel>
  <programme channel="403674" start="20250528002000 +0000" stop="20250528005000 +0000">
    <title lang="zh">Bluey</title>
  <icon src="https://cdn-images.dzcdn.net/images/artist/738bd26f2c031830bcddbe883411fcca/1900x1900-000000-80-0-0.jpg"/>
  <category lang="en">Series</category>
  <category lang="en">Animation</category>
  <category lang="en">Comedy</category>
  <category lang="en">Drama</category>
  <category lang="en">Kids</category>
    <desc>Bluey and Bingo make mud pizzas; Bluey and Bingo's giant, invisible friend, Tina; Bluey promises her customer Bingo the best tour ever.</desc>
    <date>2025-05-28</date>
  </programme>
  <programme channel="403674" start="20250528005000 +0000" stop="20250528011500 +0000">
    <title lang="zh">Bluey</title>
  <icon src="https://cdn-images.dzcdn.net/images/artist/738bd26f2c031830bcddbe883411fcca/1900x1900-000000-80-0-0.jpg"/>
  <category lang="en">Series</category>
  <category lang="en">Animation</category>
  <category lang="en">Comedy</category>
  <category lang="en">Drama</category>
  <category lang="en">Kids</category>
    <desc>Bluey decides to be Mum during a game of "Kids!"; Butterflies is a fun game until Bingo ends up alone; Bluey's eyes are opened to the simple beauty of nature.</desc>
    <date>2025-05-28</date>
  </programme>
  <programme channel="403674" start="20250528011500 +0000" stop="20250528014500 +0000">
    <title lang="zh">Bluey</title>
  <icon src="https://cdn-images.dzcdn.net/images/artist/738bd26f2c031830bcddbe883411fcca/1900x1900-000000-80-0-0.jpg"/>
  <category lang="en">Series</category>
  <category lang="en">Animation</category>
  <category lang="en">Comedy</category>
  <category lang="en">Drama</category>
  <category lang="en">Kids</category>
    <desc>The adventures of a Blue Heeler puppy, Bluey, who lives with her mother, father and sister; her energy and lovable spirit gets her into all kinds of funny and unpredictable situations.</desc>
    <date>2025-05-28</date>
  </programme>
  <programme channel="403674" start="20250528014500 +0000" stop="20250528015500 +0000">
    <title lang="zh">Bluey</title>
  <icon src="https://cdn-images.dzcdn.net/images/artist/738bd26f2c031830bcddbe883411fcca/1900x1900-000000-80-0-0.jpg"/>
  <category lang="en">Series</category>
  <category lang="en">Animation</category>
  <category lang="en">Comedy</category>
  <category lang="en">Drama</category>
  <category lang="en">Kids</category>
    <desc>When the girls build couch-cushion playhouses with Mum, Bluey needs her advice on dealing with Bingo, her troublesome neighbor.</desc>
    <date>2025-05-28</date>
  </programme>
  <programme channel="403674" start="20250528015500 +0000" stop="20250528022500 +0000">
    <title lang="zh">SuperKitties</title>
    <desc>Wiggles learns how to fly to free the team from Cat Burglar; Mr. Puppypaws' glittery baby dragons battle the SuperKitties as they try to stop him from not sharing the Zoomie Zone.</desc>
    <date>2025-05-28</date>
  </programme>
  <programme channel="403674" start="20250528022500 +0000" stop="20250528025000 +0000">
    <title lang="zh">Marvel's Spidey and His Amazing Friends</title>
    <desc>After Doc Ock hurts CAL's feelings, Team Spidey steps in to help; Gobby steals Miles and Spidey's powers and accidentally puts them in Bootsie.</desc>
    <date>2025-05-28</date>
  </programme>
  <programme channel="403674" start="20250528025000 +0000" stop="20250528031500 +0000">
    <title lang="zh">Marvel's Spidey and His Amazing Friends</title>
    <desc>Gobby and Rhino steal Lockjaw, a teleporting pup, in hopes of making him an accomplice; when Zola traps The Thing, Spidey and Ghost-Spider under a dome, Miles must save the day.</desc>
    <date>2025-05-28</date>
  </programme>
  <programme channel="403674" start="20250528031500 +0000" stop="20250528034000 +0000">
    <title lang="zh">Mickey Mouse Funhouse</title>
    <desc>Daisy searches Dreamland for her favorite dream; Daisy is dissatisfied when she wants to take the perfect selfie.</desc>
    <date>2025-05-28</date>
  </programme>
  <programme channel="403674" start="20250528034000 +0000" stop="20250528040500 +0000">
    <title lang="zh">Bluey</title>
  <icon src="https://cdn-images.dzcdn.net/images/artist/738bd26f2c031830bcddbe883411fcca/1900x1900-000000-80-0-0.jpg"/>
  <category lang="en">Series</category>
  <category lang="en">Animation</category>
  <category lang="en">Comedy</category>
  <category lang="en">Drama</category>
  <category lang="en">Kids</category>
    <desc>The adventures of a Blue Heeler puppy, Bluey, who lives with her mother, father and sister; her energy and lovable spirit gets her into all kinds of funny and unpredictable situations.</desc>
    <date>2025-05-28</date>
  </programme>
  <programme channel="403674" start="20250528040500 +0000" stop="20250528043000 +0000">
    <title lang="zh">Bluey</title>
  <icon src="https://cdn-images.dzcdn.net/images/artist/738bd26f2c031830bcddbe883411fcca/1900x1900-000000-80-0-0.jpg"/>
  <category lang="en">Series</category>
  <category lang="en">Animation</category>
  <category lang="en">Comedy</category>
  <category lang="en">Drama</category>
  <category lang="en">Kids</category>
    <desc>Dad tries to teach Bluey how to play chess, but Mom thinks she is still too young; Bingo helps Mom make an omelette for Dad's birthday; Lucky's Dad is outraged that modern Pass the Parcel has a present in every layer.</desc>
    <date>2025-05-28</date>
  </programme>
  <programme channel="403674" start="20250528043000 +0000" stop="20250528045500 +0000">
    <title lang="zh">Marvel's Spidey and His Amazing Friends</title>
    <desc>Electro and her electric gauntlet drain the power from the city's new wind turbine; Team Spidey runs up against villains who are trying to stop them from performing at a concert.</desc>
    <date>2025-05-28</date>
  </programme>
  <programme channel="403674" start="20250528045500 +0000" stop="20250528052000 +0000">
    <title lang="zh">Marvel's Spidey and His Amazing Friends</title>
    <desc>Spidey and Iron Man must fix their new invention before Sandman turns Central Park into Sandman Park; Miles can't let Rhino steal the tomatoes his mom grew for the community dinner.</desc>
    <date>2025-05-28</date>
  </programme>
  <programme channel="403674" start="20250528052000 +0000" stop="20250528054500 +0000">
    <title lang="zh">Bluey</title>
  <icon src="https://cdn-images.dzcdn.net/images/artist/738bd26f2c031830bcddbe883411fcca/1900x1900-000000-80-0-0.jpg"/>
  <category lang="en">Series</category>
  <category lang="en">Animation</category>
  <category lang="en">Comedy</category>
  <category lang="en">Drama</category>
  <category lang="en">Kids</category>
    <desc>The adventures of a Blue Heeler puppy, Bluey, who lives with her mother, father and sister; her energy and lovable spirit gets her into all kinds of funny and unpredictable situations.</desc>
    <date>2025-05-28</date>
  </programme>
  <programme channel="403674" start="20250528054500 +0000" stop="20250528061000 +0000">
    <title lang="zh">Bluey</title>
  <icon src="https://cdn-images.dzcdn.net/images/artist/738bd26f2c031830bcddbe883411fcca/1900x1900-000000-80-0-0.jpg"/>
  <category lang="en">Series</category>
  <category lang="en">Animation</category>
  <category lang="en">Comedy</category>
  <category lang="en">Drama</category>
  <category lang="en">Kids</category>
    <desc>Bingo finds a toy turtle at the playground and wants to take him home; Mom's sister Brandy comes over for a visit; Bluey and Bingo hide under the house and spy on two mysterious tradies working in the backyard.</desc>
    <date>2025-05-28</date>
  </programme>
  <programme channel="403674" start="20250528061000 +0000" stop="20250528063500 +0000">
    <title lang="zh">Bluey</title>
  <icon src="https://cdn-images.dzcdn.net/images/artist/738bd26f2c031830bcddbe883411fcca/1900x1900-000000-80-0-0.jpg"/>
  <category lang="en">Series</category>
  <category lang="en">Animation</category>
  <category lang="en">Comedy</category>
  <category lang="en">Drama</category>
  <category lang="en">Kids</category>
    <desc>Dad is accused of fluffing in Bluey's face; Bluey and Mackenzie play with two older friends; Bluey and Bingo want Dad all to themselves.</desc>
    <date>2025-05-28</date>
  </programme>
  <programme channel="403674" start="20250528063500 +0000" stop="20250528070000 +0000">
    <title lang="zh">Bluey</title>
  <icon src="https://cdn-images.dzcdn.net/images/artist/738bd26f2c031830bcddbe883411fcca/1900x1900-000000-80-0-0.jpg"/>
  <category lang="en">Series</category>
  <category lang="en">Animation</category>
  <category lang="en">Comedy</category>
  <category lang="en">Drama</category>
  <category lang="en">Kids</category>
    <desc>Bluey and Bingo plan to stay up late at a sleepover; Bluey needs to focus during a game of hide-and-seek; Bluey makes a new friend while camping.</desc>
    <date>2025-05-28</date>
  </programme>
  <programme channel="403674" start="20250528070000 +0000" stop="20250528072500 +0000">
    <title lang="zh">Bluey</title>
  <icon src="https://cdn-images.dzcdn.net/images/artist/738bd26f2c031830bcddbe883411fcca/1900x1900-000000-80-0-0.jpg"/>
  <category lang="en">Series</category>
  <category lang="en">Animation</category>
  <category lang="en">Comedy</category>
  <category lang="en">Drama</category>
  <category lang="en">Kids</category>
    <desc>Honey's trip to Dr. Bingo keeps getting interrupted; Mum and Dad create their own Magic Claw machine; Bluey takes her tooth fairy money to the market.</desc>
    <date>2025-05-28</date>
  </programme>
  <programme channel="403674" start="20250528072500 +0000" stop="20250528075000 +0000">
    <title lang="zh">Bluey</title>
  <icon src="https://cdn-images.dzcdn.net/images/artist/738bd26f2c031830bcddbe883411fcca/1900x1900-000000-80-0-0.jpg"/>
  <category lang="en">Series</category>
  <category lang="en">Animation</category>
  <category lang="en">Comedy</category>
  <category lang="en">Drama</category>
  <category lang="en">Kids</category>
    <desc>Bluey can't get to sleep, so Mum reads her a story; Dad pretends he was born yesterday; Bingo and Dad brave a magpie protecting its nest.</desc>
    <date>2025-05-28</date>
  </programme>
  <programme channel="403674" start="20250528075000 +0000" stop="20250528081500 +0000">
    <title lang="zh">Bluey</title>
  <icon src="https://cdn-images.dzcdn.net/images/artist/738bd26f2c031830bcddbe883411fcca/1900x1900-000000-80-0-0.jpg"/>
  <category lang="en">Series</category>
  <category lang="en">Animation</category>
  <category lang="en">Comedy</category>
  <category lang="en">Drama</category>
  <category lang="en">Kids</category>
    <desc>The adventures of a Blue Heeler puppy, Bluey, who lives with her mother, father and sister; her energy and lovable spirit gets her into all kinds of funny and unpredictable situations.</desc>
    <date>2025-05-28</date>
  </programme>
  <programme channel="403674" start="20250528081500 +0000" stop="20250528084000 +0000">
    <title lang="zh">Mickey and the Roadster Racers</title>
    <desc>After Von Drake invents a truck to carry all the Roadsters, Commander Heist steals it; Hilda asks the Happy Helpers to help her find a new sport to play.</desc>
    <date>2025-05-28</date>
  </programme>
  <programme channel="403674" start="20250528084000 +0000" stop="20250528090500 +0000">
    <title lang="zh">Mickey and the Roadster Racers</title>
    <desc>During Chef Pierre's cafe opening, Goofy's famous Goofy Dogs are stolen; when the Happy Helpers return to Paris, Cuckoo Loca discovers new family members.</desc>
    <date>2025-05-28</date>
  </programme>
  <programme channel="403674" start="20250528090500 +0000" stop="20250528093000 +0000">
    <title lang="zh">Mickey Mouse Clubhouse</title>
  <icon src="https://play-lh.googleusercontent.com/bqEcu3u2ZXANY_HqhPAgfGvi4_UZ9m7wNHuz3gFjn2Urxw745-D6Va-e4Fh-Im806mMI8kFDhQWAFmLZM7c"/>
  <category lang="en">Educational</category>
  <category lang="en">Animation</category>
  <category lang="en">Comedy</category>
  <category lang="en">Kids</category>
    <desc>It's Pluto's turn to tell a story; Pluto chooses the tale of a pup that wins a golden ball and is pursued by Sneaky Pete.</desc>
    <date>2025-05-28</date>
  </programme>
  <programme channel="403674" start="20250528093000 +0000" stop="20250528100000 +0000">
    <title lang="zh">Mickey Mouse Clubhouse</title>
  <icon src="https://play-lh.googleusercontent.com/bqEcu3u2ZXANY_HqhPAgfGvi4_UZ9m7wNHuz3gFjn2Urxw745-D6Va-e4Fh-Im806mMI8kFDhQWAFmLZM7c"/>
  <category lang="en">Educational</category>
  <category lang="en">Animation</category>
  <category lang="en">Comedy</category>
  <category lang="en">Kids</category>
    <desc>Minnie enlists Mickey and his friends to help plan a picnic.</desc>
    <date>2025-05-28</date>
  </programme>
  <programme channel="403674" start="20250528100000 +0000" stop="20250528102500 +0000">
    <title lang="zh">Bluey</title>
  <icon src="https://cdn-images.dzcdn.net/images/artist/738bd26f2c031830bcddbe883411fcca/1900x1900-000000-80-0-0.jpg"/>
  <category lang="en">Series</category>
  <category lang="en">Animation</category>
  <category lang="en">Comedy</category>
  <category lang="en">Drama</category>
  <category lang="en">Kids</category>
    <desc>Mum and Dad need to finish their housework; Dad, Bluey and Bingo play Sheepdog; Jack pretends to be a sailor on his way home.</desc>
    <date>2025-05-28</date>
  </programme>
  <programme channel="403674" start="20250528102500 +0000" stop="20250528110000 +0000">
    <title lang="zh">Mickey Mouse Clubhouse</title>
  <icon src="https://play-lh.googleusercontent.com/bqEcu3u2ZXANY_HqhPAgfGvi4_UZ9m7wNHuz3gFjn2Urxw745-D6Va-e4Fh-Im806mMI8kFDhQWAFmLZM7c"/>
  <category lang="en">Educational</category>
  <category lang="en">Animation</category>
  <category lang="en">Comedy</category>
  <category lang="en">Kids</category>
    <desc>Pluto plays games with Pete's dog Butch to see who will win a trophy.</desc>
    <date>2025-05-28</date>
  </programme>
  <programme channel="403674" start="20250528110000 +0000" stop="20250528113000 +0000">
    <title lang="zh">Mickey Mouse Funhouse</title>
    <desc>When Funny needs a plumber, he tries to distract the gang with errands to avoid a visit from the funhouse doctor; Funny takes everyone to Big Fish Swamp to go fishing.</desc>
    <date>2025-05-28</date>
  </programme>
  <programme channel="403674" start="20250528113000 +0000" stop="20250528120000 +0000">
    <title lang="zh">Bluey</title>
  <icon src="https://cdn-images.dzcdn.net/images/artist/738bd26f2c031830bcddbe883411fcca/1900x1900-000000-80-0-0.jpg"/>
  <category lang="en">Series</category>
  <category lang="en">Animation</category>
  <category lang="en">Comedy</category>
  <category lang="en">Drama</category>
  <category lang="en">Kids</category>
    <desc>Bluey, Bingo and Mum enjoy a game of Keepy-Uppy around the house; Bluey and Bingo squabble over their magic xylophone; Coco keeps taking shortcuts while playing Shadowlands.</desc>
    <date>2025-05-28</date>
  </programme>
  <programme channel="403674" start="20250528120000 +0000" stop="20250528123000 +0000">
    <title lang="zh">Robogobo</title>
    <desc>The story of five adorable pets without a home. A kid inventor named Dax adopts them and gives them super-powered robo-suits.</desc>
    <date>2025-05-28</date>
  </programme>
  <programme channel="403674" start="20250528123000 +0000" stop="20250528130000 +0000">
    <title lang="zh">Bluey</title>
  <icon src="https://cdn-images.dzcdn.net/images/artist/738bd26f2c031830bcddbe883411fcca/1900x1900-000000-80-0-0.jpg"/>
  <category lang="en">Series</category>
  <category lang="en">Animation</category>
  <category lang="en">Comedy</category>
  <category lang="en">Drama</category>
  <category lang="en">Kids</category>
    <desc>The slice-of-life adventures of an Australian Blue Heeler Cattle Dog puppy.</desc>
    <date>2025-05-28</date>
  </programme>
  <programme channel="403674" start="20250528130000 +0000" stop="20250528132500 +0000">
    <title lang="zh">Disney Jr's Ariel</title>
    <desc>A new fish wants an adventure of her own; Triton accidentally turns into a kid.</desc>
    <date>2025-05-28</date>
  </programme>
  <programme channel="403674" start="20250528132500 +0000" stop="20250528135000 +0000">
    <title lang="zh">Mickey Mouse Funhouse</title>
    <desc>When a new player who won't share causes his players to quit, Pete calls the gang to play a baseball game; Goofy helps Lunar Clarabelle learn to make hot dogs.</desc>
    <date>2025-05-28</date>
  </programme>
  <programme channel="403674" start="20250528135000 +0000" stop="20250528141500 +0000">
    <title lang="zh">Bluey</title>
  <icon src="https://cdn-images.dzcdn.net/images/artist/738bd26f2c031830bcddbe883411fcca/1900x1900-000000-80-0-0.jpg"/>
  <category lang="en">Series</category>
  <category lang="en">Animation</category>
  <category lang="en">Comedy</category>
  <category lang="en">Drama</category>
  <category lang="en">Kids</category>
    <desc>Dad is accused of fluffing in Bluey's face; Bluey and Mackenzie play with two older friends; Bluey and Bingo want Dad all to themselves.</desc>
    <date>2025-05-28</date>
  </programme>
  <programme channel="403674" start="20250528141500 +0000" stop="20250528144000 +0000">
    <title lang="zh">SuperKitties</title>
    <desc>The SuperKitties must rescue Wiggles, their new dancing robo-piggy, from Zsa-Zsa before the Kittydale Dance Party; Bitsy cheers on Pickles as he learns something new.</desc>
    <date>2025-05-28</date>
  </programme>
  <programme channel="403674" start="20250528144000 +0000" stop="20250528150500 +0000">
    <title lang="zh">SuperKitties</title>
    <desc>Lab Rat tries to stop Ginny's hero, Polaris the Astro-Cat, from being the first cat on the moon; the SuperKitties must catch Zsa-Zsa when she steals a special gem from the museum.</desc>
    <date>2025-05-28</date>
  </programme>
  <programme channel="403674" start="20250528150500 +0000" stop="20250528152500 +0000">
    <title lang="zh">Bluey</title>
  <icon src="https://cdn-images.dzcdn.net/images/artist/738bd26f2c031830bcddbe883411fcca/1900x1900-000000-80-0-0.jpg"/>
  <category lang="en">Series</category>
  <category lang="en">Animation</category>
  <category lang="en">Comedy</category>
  <category lang="en">Drama</category>
  <category lang="en">Kids</category>
    <desc>Bluey gets her own room; Bluey wants her Father's Day card to be perfect; Mum sets up a backyard obstacle course just for fun.</desc>
    <date>2025-05-28</date>
  </programme>
  <programme channel="403674" start="20250528152500 +0000" stop="20250528154500 +0000">
    <title lang="zh">Bluey</title>
  <icon src="https://cdn-images.dzcdn.net/images/artist/738bd26f2c031830bcddbe883411fcca/1900x1900-000000-80-0-0.jpg"/>
  <category lang="en">Series</category>
  <category lang="en">Animation</category>
  <category lang="en">Comedy</category>
  <category lang="en">Drama</category>
  <category lang="en">Kids</category>
    <desc>Dad plays trampoline games with Bluey and Bingo; Dad plans on throwing out Bluey's old drawings; Bingo causes chaos at Bluey's backyard zoo.</desc>
    <date>2025-05-28</date>
  </programme>
  <programme channel="403674" start="20250528154500 +0000" stop="20250528161000 +0000">
    <title lang="zh">Pupstruction</title>
    <desc>Race car driver Shell Shelby enlists Pupstruction's help in breaking a speed record; Bobby enlists Murphy's accident-prone help to ruin Pupstruction's bridge build.</desc>
    <date>2025-05-28</date>
  </programme>
  <programme channel="403674" start="20250528161000 +0000" stop="20250528163500 +0000">
    <title lang="zh">Bluey</title>
  <icon src="https://cdn-images.dzcdn.net/images/artist/738bd26f2c031830bcddbe883411fcca/1900x1900-000000-80-0-0.jpg"/>
  <category lang="en">Series</category>
  <category lang="en">Animation</category>
  <category lang="en">Comedy</category>
  <category lang="en">Drama</category>
  <category lang="en">Kids</category>
    <desc>The Heelers take a trip to Hammerbarn; Bingo has an idea for a new game; Dad eats Bingo's last chip.</desc>
    <date>2025-05-28</date>
  </programme>
  <programme channel="403674" start="20250528163500 +0000" stop="20250528170000 +0000">
    <title lang="zh">Marvel's Spidey and His Amazing Friends</title>
    <desc>Doc Ock's new invention turns people into frozen statues; Team Spidey must save Jeff when he accidentally tries on Spidey's new Web-Spinner boots.</desc>
    <date>2025-05-28</date>
  </programme>
  <programme channel="403674" start="20250528170000 +0000" stop="20250528172500 +0000">
    <title lang="zh">Marvel's Spidey and His Amazing Friends</title>
    <desc>Miles' Father's Day fishing trip is interrupted by Doc Ock's plan to take over the harbor; Spidey, Hulk and Ms. Marvel get in over their heads when a squirrel wreaks havoc.</desc>
    <date>2025-05-28</date>
  </programme>
  <programme channel="403674" start="20250528172500 +0000" stop="20250528175000 +0000">
    <title lang="zh">SuperKitties</title>
    <desc>The SuperKitties must find the real thief when animals accuse Sparks of stealing; a jealous Mr. Puppypaws traps all the other dogs to keep them away from the park.</desc>
    <date>2025-05-28</date>
  </programme>
  <programme channel="403674" start="20250528175000 +0000" stop="20250528183000 +0000">
    <title lang="zh">SuperKitties</title>
    <desc>Lab Rat controls the Burble toys to steal all the cheese in Kittydale; the SuperKitties stop Mr. Puppypaws from turning all the wood in the park into fetching sticks.</desc>
    <date>2025-05-28</date>
  </programme>
  <programme channel="403674" start="20250528183000 +0000" stop="20250528185500 +0000">
    <title lang="zh">Marvel's Spidey and His Amazing Friends</title>
    <desc>Spidey and Iron Man must fix their new invention before Sandman turns Central Park into Sandman Park; Miles can't let Rhino steal the tomatoes his mom grew for the community dinner.</desc>
    <date>2025-05-28</date>
  </programme>
  <programme channel="403674" start="20250528185500 +0000" stop="20250528192000 +0000">
    <title lang="zh">Bluey</title>
  <icon src="https://cdn-images.dzcdn.net/images/artist/738bd26f2c031830bcddbe883411fcca/1900x1900-000000-80-0-0.jpg"/>
  <category lang="en">Series</category>
  <category lang="en">Animation</category>
  <category lang="en">Comedy</category>
  <category lang="en">Drama</category>
  <category lang="en">Kids</category>
    <desc>The Heelers play a game of Bus; Mum and Bluey play Mum School, where Mum teaches Bluey how to corral her rowdy kids; Bingo decides she's too tired to walk and needs a piggyback.</desc>
    <date>2025-05-28</date>
  </programme>
  <programme channel="403674" start="20250528192000 +0000" stop="20250528194500 +0000">
    <title lang="zh">Bluey</title>
  <icon src="https://cdn-images.dzcdn.net/images/artist/738bd26f2c031830bcddbe883411fcca/1900x1900-000000-80-0-0.jpg"/>
  <category lang="en">Series</category>
  <category lang="en">Animation</category>
  <category lang="en">Comedy</category>
  <category lang="en">Drama</category>
  <category lang="en">Kids</category>
    <desc>At the pharmacy, Bluey and Bingo have fun playing with the CCTV screens.</desc>
    <date>2025-05-28</date>
  </programme>
  <programme channel="403674" start="20250528194500 +0000" stop="20250528201500 +0000">
    <title lang="zh">Kindergarten: The Musical</title>
    <desc>Radish tries to remember all the special things about his grandma, Lola Gloria; the kids play Library, but Tej doesn't want to wait in line to check out the new dinosaur book!</desc>
    <date>2025-05-28</date>
  </programme>
  <programme channel="403674" start="20250528201500 +0000" stop="20250528204500 +0000">
    <title lang="zh">Bluey</title>
  <icon src="https://cdn-images.dzcdn.net/images/artist/738bd26f2c031830bcddbe883411fcca/1900x1900-000000-80-0-0.jpg"/>
  <category lang="en">Series</category>
  <category lang="en">Animation</category>
  <category lang="en">Comedy</category>
  <category lang="en">Drama</category>
  <category lang="en">Kids</category>
    <desc>Indy and Rusty can't agree in a game of Mum and Dads; Bluey and Bingo work together to climb Mount MumandDad; magic asparagus turns the family into wild animals.</desc>
    <date>2025-05-28</date>
  </programme>
  <programme channel="403674" start="20250528204500 +0000" stop="20250528211500 +0000">
    <title lang="zh">Bluey</title>
  <icon src="https://cdn-images.dzcdn.net/images/artist/738bd26f2c031830bcddbe883411fcca/1900x1900-000000-80-0-0.jpg"/>
  <category lang="en">Series</category>
  <category lang="en">Animation</category>
  <category lang="en">Comedy</category>
  <category lang="en">Drama</category>
  <category lang="en">Kids</category>
    <desc>Invisible mischievous fairies infest the house; Bluey, Bingo and Dad play "Work!"; Bluey and Dad lift Bingo's spirits.</desc>
    <date>2025-05-28</date>
  </programme>
  <programme channel="403674" start="20250528211500 +0000" stop="20250528214500 +0000">
    <title lang="zh">SuperKitties</title>
    <desc>The SuperKitties stop Cat Burglar from stealing the trendy new hats in Kittydale; Buddy doesn't give up on learning how to use a telescope.</desc>
    <date>2025-05-28</date>
  </programme>
  <programme channel="403674" start="20250528214500 +0000" stop="20250528221500 +0000">
    <title lang="zh">Bluey</title>
  <icon src="https://cdn-images.dzcdn.net/images/artist/738bd26f2c031830bcddbe883411fcca/1900x1900-000000-80-0-0.jpg"/>
  <category lang="en">Series</category>
  <category lang="en">Animation</category>
  <category lang="en">Comedy</category>
  <category lang="en">Drama</category>
  <category lang="en">Kids</category>
    <desc>Jack and Rusty play Army at school; the girls set up a fancy restaurant for Mum and Dad; Bluey, Bingo and Muffin strike a deal with the dads.</desc>
    <date>2025-05-28</date>
  </programme>
  <programme channel="403674" start="20250528221500 +0000" stop="20250528224000 +0000">
    <title lang="zh">Bluey</title>
  <icon src="https://cdn-images.dzcdn.net/images/artist/738bd26f2c031830bcddbe883411fcca/1900x1900-000000-80-0-0.jpg"/>
  <category lang="en">Series</category>
  <category lang="en">Animation</category>
  <category lang="en">Comedy</category>
  <category lang="en">Drama</category>
  <category lang="en">Kids</category>
    <desc>Bluey keeps breaking her promises; Bluey teaches Bingo how to use magic; Bluey teaches Bingo to be more like him.</desc>
    <date>2025-05-28</date>
  </programme>
  <programme channel="403674" start="20250528224000 +0000" stop="20250528230500 +0000">
    <title lang="zh">Marvel's Spidey and His Amazing Friends</title>
    <desc>Spin accidentally puts his own arm to sleep with his arachno-sting.</desc>
    <date>2025-05-28</date>
  </programme>
  <programme channel="403674" start="20250528230500 +0000" stop="20250528233000 +0000">
    <title lang="zh">Robogobo</title>
    <desc>When Risky and Royale pretend to be in danger so RoboGobo will rescue them, they end up needing a real rescue; Dax and Allie help a jaguar cub with limb difference save his sisters.</desc>
    <date>2025-05-28</date>
  </programme>
  <programme channel="403674" start="20250528233000 +0000" stop="20250528235500 +0000">
    <title lang="zh">Marvel's Spidey and His Amazing Friends</title>
    <desc>Team Spidey must save the art show when Zola steals artwork from the museum; Spidey and Black Panther must catch runaway new tech lost in the city before Doc Ock finds it.</desc>
    <date>2025-05-28</date>
  </programme>
  <programme channel="403674" start="20250528235500 +0000" stop="20250529000000 +0000">
    <title lang="zh">Bluey</title>
  <icon src="https://cdn-images.dzcdn.net/images/artist/738bd26f2c031830bcddbe883411fcca/1900x1900-000000-80-0-0.jpg"/>
  <category lang="en">Series</category>
  <category lang="en">Animation</category>
  <category lang="en">Comedy</category>
  <category lang="en">Drama</category>
  <category lang="en">Kids</category>
    <desc>The adventures of a Blue Heeler puppy, Bluey, who lives with her mother, father and sister; her energy and lovable spirit gets her into all kinds of funny and unpredictable situations.</desc>
    <date>2025-05-28</date>
  </programme>
  <programme channel="403674" start="20250529002000 +0000" stop="20250529005000 +0000">
    <title lang="zh">Bluey</title>
  <icon src="https://cdn-images.dzcdn.net/images/artist/738bd26f2c031830bcddbe883411fcca/1900x1900-000000-80-0-0.jpg"/>
  <category lang="en">Series</category>
  <category lang="en">Animation</category>
  <category lang="en">Comedy</category>
  <category lang="en">Drama</category>
  <category lang="en">Kids</category>
    <desc>Mum and Dad need to finish their housework; Dad, Bluey and Bingo play Sheepdog; Jack pretends to be a sailor on his way home.</desc>
    <date>2025-05-29</date>
  </programme>
  <programme channel="403674" start="20250529005000 +0000" stop="20250529011500 +0000">
    <title lang="zh">Bluey</title>
  <icon src="https://cdn-images.dzcdn.net/images/artist/738bd26f2c031830bcddbe883411fcca/1900x1900-000000-80-0-0.jpg"/>
  <category lang="en">Series</category>
  <category lang="en">Animation</category>
  <category lang="en">Comedy</category>
  <category lang="en">Drama</category>
  <category lang="en">Kids</category>
    <desc>Bluey, Bingo and Mum enjoy a game of Keepy-Uppy around the house; Bluey and Bingo squabble over their magic xylophone; Coco keeps taking shortcuts while playing Shadowlands.</desc>
    <date>2025-05-29</date>
  </programme>
  <programme channel="403674" start="20250529011500 +0000" stop="20250529014500 +0000">
    <title lang="zh">Bluey</title>
  <icon src="https://cdn-images.dzcdn.net/images/artist/738bd26f2c031830bcddbe883411fcca/1900x1900-000000-80-0-0.jpg"/>
  <category lang="en">Series</category>
  <category lang="en">Animation</category>
  <category lang="en">Comedy</category>
  <category lang="en">Drama</category>
  <category lang="en">Kids</category>
    <desc>The slice-of-life adventures of an Australian Blue Heeler Cattle Dog puppy.</desc>
    <date>2025-05-29</date>
  </programme>
  <programme channel="403674" start="20250529014500 +0000" stop="20250529015500 +0000">
    <title lang="zh">Bluey</title>
  <icon src="https://cdn-images.dzcdn.net/images/artist/738bd26f2c031830bcddbe883411fcca/1900x1900-000000-80-0-0.jpg"/>
  <category lang="en">Series</category>
  <category lang="en">Animation</category>
  <category lang="en">Comedy</category>
  <category lang="en">Drama</category>
  <category lang="en">Kids</category>
    <desc>When Bingo and Bluey visit their cousin's house for a sleepover, they take this opportunity to stay up late; when Muffin arrives very tired from not taking her nap, the girls have more fun than they expected.</desc>
    <date>2025-05-29</date>
  </programme>
  <programme channel="403674" start="20250529015500 +0000" stop="20250529022500 +0000">
    <title lang="zh">SuperKitties</title>
    <desc>When Ginny gets a boo-boo, Sparks, Buddy and Bitsy have to learn to work as a team without her; the SuperKitties help Peanut get Nadia's stolen toy car back from Zsa-Zsa.</desc>
    <date>2025-05-29</date>
  </programme>
  <programme channel="403674" start="20250529022500 +0000" stop="20250529025000 +0000">
    <title lang="zh">Marvel's Spidey and His Amazing Friends</title>
    <desc>Green Goblin decides to quit being a villain and become a good guy; Rhino steals a Spider Monkey from the zoo, and it's up to Spidey and Ghost-Spider to bring him home.</desc>
    <date>2025-05-29</date>
  </programme>
  <programme channel="403674" start="20250529025000 +0000" stop="20250529031500 +0000">
    <title lang="zh">Marvel's Spidey and His Amazing Friends</title>
    <desc>When Doc Ock steals the arachno-sting power, Team Spidey has to get it back before she puts the town to sleep; Green Goblin and Rhino take over a bridge and threaten to destroy it.</desc>
    <date>2025-05-29</date>
  </programme>
  <programme channel="403674" start="20250529031500 +0000" stop="20250529034000 +0000">
    <title lang="zh">Mickey Mouse Funhouse</title>
    <desc>The superheroes of Herotropolis are gone; Weasels and the gang make a huge mess; Daisy thinks Donald is cheating at their games, but learns good friends should believe each other.</desc>
    <date>2025-05-29</date>
  </programme>
  <programme channel="403674" start="20250529034000 +0000" stop="20250529040500 +0000">
    <title lang="zh">Bluey</title>
  <icon src="https://cdn-images.dzcdn.net/images/artist/738bd26f2c031830bcddbe883411fcca/1900x1900-000000-80-0-0.jpg"/>
  <category lang="en">Series</category>
  <category lang="en">Animation</category>
  <category lang="en">Comedy</category>
  <category lang="en">Drama</category>
  <category lang="en">Kids</category>
    <desc>Bluey gets her own room; Bluey wants her Father's Day card to be perfect; Mum sets up a backyard obstacle course just for fun.</desc>
    <date>2025-05-29</date>
  </programme>
  <programme channel="403674" start="20250529040500 +0000" stop="20250529043000 +0000">
    <title lang="zh">Bluey</title>
  <icon src="https://cdn-images.dzcdn.net/images/artist/738bd26f2c031830bcddbe883411fcca/1900x1900-000000-80-0-0.jpg"/>
  <category lang="en">Series</category>
  <category lang="en">Animation</category>
  <category lang="en">Comedy</category>
  <category lang="en">Drama</category>
  <category lang="en">Kids</category>
    <desc>Dad plays trampoline games with Bluey and Bingo; Dad plans on throwing out Bluey's old drawings; Bingo causes chaos at Bluey's backyard zoo.</desc>
    <date>2025-05-29</date>
  </programme>
  <programme channel="403674" start="20250529043000 +0000" stop="20250529045500 +0000">
    <title lang="zh">Marvel's Spidey and His Amazing Friends</title>
    <desc>Team Spidey and Black Cat join forces to stop Doc Ock from destroying the Maltese kitten; Miles and Black Panther's special day is nearly spoiled by Electro.</desc>
    <date>2025-05-29</date>
  </programme>
  <programme channel="403674" start="20250529045500 +0000" stop="20250529052000 +0000">
    <title lang="zh">Marvel's Spidey and His Amazing Friends</title>
    <desc>Gwen teams up with her dad to save the forest from Doc Ock; Peter accidentally grows his pet ant to the size of a dog.</desc>
    <date>2025-05-29</date>
  </programme>
  <programme channel="403674" start="20250529052000 +0000" stop="20250529054500 +0000">
    <title lang="zh">Bluey</title>
  <icon src="https://cdn-images.dzcdn.net/images/artist/738bd26f2c031830bcddbe883411fcca/1900x1900-000000-80-0-0.jpg"/>
  <category lang="en">Series</category>
  <category lang="en">Animation</category>
  <category lang="en">Comedy</category>
  <category lang="en">Drama</category>
  <category lang="en">Kids</category>
    <desc>The Heelers take a trip to Hammerbarn; Bingo has an idea for a new game; Dad eats Bingo's last chip.</desc>
    <date>2025-05-29</date>
  </programme>
  <programme channel="403674" start="20250529054500 +0000" stop="20250529061000 +0000">
    <title lang="zh">Bluey</title>
  <icon src="https://cdn-images.dzcdn.net/images/artist/738bd26f2c031830bcddbe883411fcca/1900x1900-000000-80-0-0.jpg"/>
  <category lang="en">Series</category>
  <category lang="en">Animation</category>
  <category lang="en">Comedy</category>
  <category lang="en">Drama</category>
  <category lang="en">Kids</category>
    <desc>The Heelers play a game of Bus; Mum and Bluey play Mum School, where Mum teaches Bluey how to corral her rowdy kids; Bingo decides she's too tired to walk and needs a piggyback.</desc>
    <date>2025-05-29</date>
  </programme>
  <programme channel="403674" start="20250529061000 +0000" stop="20250529063500 +0000">
    <title lang="zh">Bluey</title>
  <icon src="https://cdn-images.dzcdn.net/images/artist/738bd26f2c031830bcddbe883411fcca/1900x1900-000000-80-0-0.jpg"/>
  <category lang="en">Series</category>
  <category lang="en">Animation</category>
  <category lang="en">Comedy</category>
  <category lang="en">Drama</category>
  <category lang="en">Kids</category>
    <desc>At the pharmacy, Bluey and Bingo have fun playing with the CCTV screens.</desc>
    <date>2025-05-29</date>
  </programme>
  <programme channel="403674" start="20250529063500 +0000" stop="20250529070000 +0000">
    <title lang="zh">Bluey</title>
  <icon src="https://cdn-images.dzcdn.net/images/artist/738bd26f2c031830bcddbe883411fcca/1900x1900-000000-80-0-0.jpg"/>
  <category lang="en">Series</category>
  <category lang="en">Animation</category>
  <category lang="en">Comedy</category>
  <category lang="en">Drama</category>
  <category lang="en">Kids</category>
    <desc>Indy and Rusty can't agree in a game of Mum and Dads; Bluey and Bingo work together to climb Mount MumandDad; magic asparagus turns the family into wild animals.</desc>
    <date>2025-05-29</date>
  </programme>
  <programme channel="403674" start="20250529070000 +0000" stop="20250529072500 +0000">
    <title lang="zh">Bluey</title>
  <icon src="https://cdn-images.dzcdn.net/images/artist/738bd26f2c031830bcddbe883411fcca/1900x1900-000000-80-0-0.jpg"/>
  <category lang="en">Series</category>
  <category lang="en">Animation</category>
  <category lang="en">Comedy</category>
  <category lang="en">Drama</category>
  <category lang="en">Kids</category>
    <desc>Invisible mischievous fairies infest the house; Bluey, Bingo and Dad play "Work!"; Bluey and Dad lift Bingo's spirits.</desc>
    <date>2025-05-29</date>
  </programme>
  <programme channel="403674" start="20250529072500 +0000" stop="20250529075000 +0000">
    <title lang="zh">Bluey</title>
  <icon src="https://cdn-images.dzcdn.net/images/artist/738bd26f2c031830bcddbe883411fcca/1900x1900-000000-80-0-0.jpg"/>
  <category lang="en">Series</category>
  <category lang="en">Animation</category>
  <category lang="en">Comedy</category>
  <category lang="en">Drama</category>
  <category lang="en">Kids</category>
    <desc>Jack and Rusty play Army at school; the girls set up a fancy restaurant for Mum and Dad; Bluey, Bingo and Muffin strike a deal with the dads.</desc>
    <date>2025-05-29</date>
  </programme>
  <programme channel="403674" start="20250529075000 +0000" stop="20250529081500 +0000">
    <title lang="zh">Bluey</title>
  <icon src="https://cdn-images.dzcdn.net/images/artist/738bd26f2c031830bcddbe883411fcca/1900x1900-000000-80-0-0.jpg"/>
  <category lang="en">Series</category>
  <category lang="en">Animation</category>
  <category lang="en">Comedy</category>
  <category lang="en">Drama</category>
  <category lang="en">Kids</category>
    <desc>Bluey keeps breaking her promises; Bluey teaches Bingo how to use magic; Bluey teaches Bingo to be more like him.</desc>
    <date>2025-05-29</date>
  </programme>
  <programme channel="403674" start="20250529081500 +0000" stop="20250529084000 +0000">
    <title lang="zh">Mickey and the Roadster Racers</title>
    <desc>Mickey challenges Professor Von Drake's Self-Racing Racer to a race; Billy Beagle asks the Happy Helpers to help his grandpa with some errands.</desc>
    <date>2025-05-29</date>
  </programme>
  <programme channel="403674" start="20250529084000 +0000" stop="20250529090500 +0000">
    <title lang="zh">Mickey and the Roadster Racers</title>
    <desc>Mickey and Goofy join the Hot Dog Hills' Invention Competition; the Happy Helpers become babysitters for the day after the Hot Dog Hills play center closes.</desc>
    <date>2025-05-29</date>
  </programme>
  <programme channel="403674" start="20250529090500 +0000" stop="20250529093000 +0000">
    <title lang="zh">Mickey Mouse Clubhouse</title>
  <icon src="https://play-lh.googleusercontent.com/bqEcu3u2ZXANY_HqhPAgfGvi4_UZ9m7wNHuz3gFjn2Urxw745-D6Va-e4Fh-Im806mMI8kFDhQWAFmLZM7c"/>
  <category lang="en">Educational</category>
  <category lang="en">Animation</category>
  <category lang="en">Comedy</category>
  <category lang="en">Kids</category>
    <desc>Mickey finds an egg that hatches into a dragon; he and his friends must convince Wizard Pete that they did not steal it.</desc>
    <date>2025-05-29</date>
  </programme>
  <programme channel="403674" start="20250529093000 +0000" stop="20250529100000 +0000">
    <title lang="zh">Mickey Mouse Clubhouse</title>
  <icon src="https://play-lh.googleusercontent.com/bqEcu3u2ZXANY_HqhPAgfGvi4_UZ9m7wNHuz3gFjn2Urxw745-D6Va-e4Fh-Im806mMI8kFDhQWAFmLZM7c"/>
  <category lang="en">Educational</category>
  <category lang="en">Animation</category>
  <category lang="en">Comedy</category>
  <category lang="en">Kids</category>
    <desc>Mickey and pals help Daisy find her new friend Wilbur the grasshopper.</desc>
    <date>2025-05-29</date>
  </programme>
  <programme channel="403674" start="20250529100000 +0000" stop="20250529102500 +0000">
    <title lang="zh">Bluey</title>
  <icon src="https://cdn-images.dzcdn.net/images/artist/738bd26f2c031830bcddbe883411fcca/1900x1900-000000-80-0-0.jpg"/>
  <category lang="en">Series</category>
  <category lang="en">Animation</category>
  <category lang="en">Comedy</category>
  <category lang="en">Drama</category>
  <category lang="en">Kids</category>
    <desc>The adventures of a Blue Heeler puppy, Bluey, who lives with her mother, father and sister; her energy and lovable spirit gets her into all kinds of funny and unpredictable situations.</desc>
    <date>2025-05-29</date>
  </programme>
  <programme channel="403674" start="20250529102500 +0000" stop="20250529110000 +0000">
    <title lang="zh">Mickey and the Roadster Racers</title>
    <desc>While participating in a ukulele jam, Donald loses Mickey's special ukulele; The Happy Helpers are judges for a Hawaiian surfing contest and learn about a lifelong rivalry.</desc>
    <date>2025-05-29</date>
  </programme>
  <programme channel="403674" start="20250529110000 +0000" stop="20250529113000 +0000">
    <title lang="zh">Mickey Mouse Funhouse</title>
    <desc>Clarabelle is overwhelmed by the things she needs to do during Pie Day; Minnie adopts a new puppy and isn't prepared to train her.</desc>
    <date>2025-05-29</date>
  </programme>
  <programme channel="403674" start="20250529113000 +0000" stop="20250529120000 +0000">
    <title lang="zh">Bluey</title>
  <icon src="https://cdn-images.dzcdn.net/images/artist/738bd26f2c031830bcddbe883411fcca/1900x1900-000000-80-0-0.jpg"/>
  <category lang="en">Series</category>
  <category lang="en">Animation</category>
  <category lang="en">Comedy</category>
  <category lang="en">Drama</category>
  <category lang="en">Kids</category>
    <desc>Rusty interrupts Bluey's game at playgroup; Doctor Bluey operates on a cat in Dad's tummy; Bluey misses Mum when she goes out for the night.</desc>
    <date>2025-05-29</date>
  </programme>
  <programme channel="403674" start="20250529120000 +0000" stop="20250529123000 +0000">
    <title lang="zh">Robogobo</title>
    <desc>When the Slink tricks Risky and Royale into joining her crew, RoboGobo must rescue them; Dax and Hopper help a scared penguin go down a slide to escape Pupsicle's Mecha-Muttsicles.</desc>
    <date>2025-05-29</date>
  </programme>
  <programme channel="403674" start="20250529123000 +0000" stop="20250529130000 +0000">
    <title lang="zh">Bluey</title>
  <icon src="https://cdn-images.dzcdn.net/images/artist/738bd26f2c031830bcddbe883411fcca/1900x1900-000000-80-0-0.jpg"/>
  <category lang="en">Series</category>
  <category lang="en">Animation</category>
  <category lang="en">Comedy</category>
  <category lang="en">Drama</category>
  <category lang="en">Kids</category>
    <desc>The adventures of a Blue Heeler puppy, Bluey, who lives with her mother, father and sister; her energy and lovable spirit gets her into all kinds of funny and unpredictable situations.</desc>
    <date>2025-05-29</date>
  </programme>
  <programme channel="403674" start="20250529130000 +0000" stop="20250529132500 +0000">
    <title lang="zh">Ariel: Mermaid Tales</title>
    <desc>Fernie forgets his blanket. Lucia makes too many plans.</desc>
    <date>2025-05-29</date>
  </programme>
  <programme channel="403674" start="20250529132500 +0000" stop="20250529135000 +0000">
    <title lang="zh">Mickey Mouse Funhouse</title>
    <desc>The Weasels steal a train full of Rocky Road ice cream to have it all for themselves; the gang and their pets are invited to a ball and Mortimer refuses to use good manners.</desc>
    <date>2025-05-29</date>
  </programme>
  <programme channel="403674" start="20250529135000 +0000" stop="20250529141500 +0000">
    <title lang="zh">Bluey</title>
  <icon src="https://cdn-images.dzcdn.net/images/artist/738bd26f2c031830bcddbe883411fcca/1900x1900-000000-80-0-0.jpg"/>
  <category lang="en">Series</category>
  <category lang="en">Animation</category>
  <category lang="en">Comedy</category>
  <category lang="en">Drama</category>
  <category lang="en">Kids</category>
    <desc>Bluey can't get to sleep, so Mum reads her a story; Dad pretends he was born yesterday; Bingo and Dad brave a magpie protecting its nest.</desc>
    <date>2025-05-29</date>
  </programme>
  <programme channel="403674" start="20250529141500 +0000" stop="20250529144000 +0000">
    <title lang="zh">SuperKitties</title>
    <desc>Mr. Puppypaws steals Bitsy's favorite toy, Mr. Greenie; the SuperKitties must return a grand piano to Petcini after Cat Burglar steals it.</desc>
    <date>2025-05-29</date>
  </programme>
  <programme channel="403674" start="20250529144000 +0000" stop="20250529150500 +0000">
    <title lang="zh">SuperKitties</title>
    <desc>Lab Rat turns Quacksley into a floatie for Otto to play on; the SuperKitties have to save Pizza Night after Cat Burglar steals all of the pizza pies for his new friend.</desc>
    <date>2025-05-29</date>
  </programme>
  <programme channel="403674" start="20250529150500 +0000" stop="20250529152500 +0000">
    <title lang="zh">Bluey</title>
  <icon src="https://cdn-images.dzcdn.net/images/artist/738bd26f2c031830bcddbe883411fcca/1900x1900-000000-80-0-0.jpg"/>
  <category lang="en">Series</category>
  <category lang="en">Animation</category>
  <category lang="en">Comedy</category>
  <category lang="en">Drama</category>
  <category lang="en">Kids</category>
    <desc>Bluey and Bingo play The Quiet Game; when Mum and Dad have a disagreement, Bluey makes Dad write a love letter to Mum; in the park, Bluey meets a new playmate, Winnie.</desc>
    <date>2025-05-29</date>
  </programme>
  <programme channel="403674" start="20250529152500 +0000" stop="20250529154500 +0000">
    <title lang="zh">Bluey</title>
  <icon src="https://cdn-images.dzcdn.net/images/artist/738bd26f2c031830bcddbe883411fcca/1900x1900-000000-80-0-0.jpg"/>
  <category lang="en">Series</category>
  <category lang="en">Animation</category>
  <category lang="en">Comedy</category>
  <category lang="en">Drama</category>
  <category lang="en">Kids</category>
    <desc>It's Bingo's turn with Kindy's Bob Bilby puppet; a game goes haywire when Bingo stops playing; five minutes feels like an eternity when waiting.</desc>
    <date>2025-05-29</date>
  </programme>
  <programme channel="403674" start="20250529154500 +0000" stop="20250529161000 +0000">
    <title lang="zh">Pupstruction</title>
    <desc>Phinny and the crew work to give Bailey some snowy fun on a warm summer day; Pupstruction builds a tower tall enough to see over the clouds by thinking outside the box.</desc>
    <date>2025-05-29</date>
  </programme>
  <programme channel="403674" start="20250529161000 +0000" stop="20250529163500 +0000">
    <title lang="zh">Bluey</title>
  <icon src="https://cdn-images.dzcdn.net/images/artist/738bd26f2c031830bcddbe883411fcca/1900x1900-000000-80-0-0.jpg"/>
  <category lang="en">Series</category>
  <category lang="en">Animation</category>
  <category lang="en">Comedy</category>
  <category lang="en">Drama</category>
  <category lang="en">Kids</category>
    <desc>Mum gets everyone to play musical statues.</desc>
    <date>2025-05-29</date>
  </programme>
  <programme channel="403674" start="20250529163500 +0000" stop="20250529170000 +0000">
    <title lang="zh">Marvel's Spidey and His Amazing Friends</title>
    <desc>The Spidey Team goes camping, but Old Dam is cracking and about to flood the park; Green Goblin frames the Hulk, and Spidey and Ghosty are determined to prove he's innocent.</desc>
    <date>2025-05-29</date>
  </programme>
  <programme channel="403674" start="20250529170000 +0000" stop="20250529172500 +0000">
    <title lang="zh">Marvel's Spidey and His Amazing Friends</title>
    <desc>When Hulk is hit with Doc Ock's Obey Ray, Team Spidey must stop him from helping her; a lemur steals Ant-Man and the Wasp's shrink and grow tech, causing trouble around the city.</desc>
    <date>2025-05-29</date>
  </programme>
  <programme channel="403674" start="20250529172500 +0000" stop="20250529175000 +0000">
    <title lang="zh">SuperKitties</title>
    <desc>The SuperKitties stop Zsa-Zsa from turning animals' voices into musical instruments; Sparks and Buddy accidentally hurt each other's feelings.</desc>
    <date>2025-05-29</date>
  </programme>
  <programme channel="403674" start="20250529175000 +0000" stop="20250529183000 +0000">
    <title lang="zh">SuperKitties</title>
    <desc>Lab Rat creates wacky weather that threatens to ruin the Pawesome Picnic; When the Kittydale Race gets sabotaged, Bitsy stops racing to help the SuperKitties save the day.</desc>
    <date>2025-05-29</date>
  </programme>
  <programme channel="403674" start="20250529183000 +0000" stop="20250529185500 +0000">
    <title lang="zh">Marvel's Spidey and His Amazing Friends</title>
    <desc>Spin gets discouraged when his hiccups keep the team from stopping Green Goblin; Spidey is in over his head when he has three things to do in one night.</desc>
    <date>2025-05-29</date>
  </programme>
  <programme channel="403674" start="20250529185500 +0000" stop="20250529192000 +0000">
    <title lang="zh">Bluey</title>
  <icon src="https://cdn-images.dzcdn.net/images/artist/738bd26f2c031830bcddbe883411fcca/1900x1900-000000-80-0-0.jpg"/>
  <category lang="en">Series</category>
  <category lang="en">Animation</category>
  <category lang="en">Comedy</category>
  <category lang="en">Drama</category>
  <category lang="en">Kids</category>
    <desc>Bluey and Bingo play restaurant with Grandad; the kids play Caf so Bingo can eat Pavlova; Bluey tracks mud into the house.</desc>
    <date>2025-05-29</date>
  </programme>
  <programme channel="403674" start="20250529192000 +0000" stop="20250529194500 +0000">
    <title lang="zh">Bluey</title>
  <icon src="https://cdn-images.dzcdn.net/images/artist/738bd26f2c031830bcddbe883411fcca/1900x1900-000000-80-0-0.jpg"/>
  <category lang="en">Series</category>
  <category lang="en">Animation</category>
  <category lang="en">Comedy</category>
  <category lang="en">Drama</category>
  <category lang="en">Kids</category>
    <desc>Bluey and Bingo want a lick of each other's ice cream; Bingo is playing Bad Mood with Dad; two babysitters turn up to look after Bluey and Bingo.</desc>
    <date>2025-05-29</date>
  </programme>
  <programme channel="403674" start="20250529194500 +0000" stop="20250529201500 +0000">
    <title lang="zh">Kindergarten: The Musical</title>
    <desc>Mami tells the class about her job on Career Day; the class's beach field trip is unexpectedly canceled, so the kids create a pretend beach day on the playground!</desc>
    <date>2025-05-29</date>
  </programme>
  <programme channel="403674" start="20250529201500 +0000" stop="20250529204500 +0000">
    <title lang="zh">Bluey</title>
  <icon src="https://cdn-images.dzcdn.net/images/artist/738bd26f2c031830bcddbe883411fcca/1900x1900-000000-80-0-0.jpg"/>
  <category lang="en">Series</category>
  <category lang="en">Animation</category>
  <category lang="en">Comedy</category>
  <category lang="en">Drama</category>
  <category lang="en">Kids</category>
    <desc>Bluey and her friends play a game of helicopter with a tree stump; Chloe tries to teach her dad to improvise and play Bluey's game of Octopus at home; Mum reminisces about Bluey and Judo as babies, where it was a race to see who would walk first.</desc>
    <date>2025-05-29</date>
  </programme>
  <programme channel="403674" start="20250529204500 +0000" stop="20250529211500 +0000">
    <title lang="zh">Bluey</title>
  <icon src="https://cdn-images.dzcdn.net/images/artist/738bd26f2c031830bcddbe883411fcca/1900x1900-000000-80-0-0.jpg"/>
  <category lang="en">Series</category>
  <category lang="en">Animation</category>
  <category lang="en">Comedy</category>
  <category lang="en">Drama</category>
  <category lang="en">Kids</category>
    <desc>Muffin plays the game of library her way; Mum, Dad and Bingo must pass swim school; Bluey, Bingo and Dad always take out the bins.</desc>
    <date>2025-05-29</date>
  </programme>
  <programme channel="403674" start="20250529211500 +0000" stop="20250529214500 +0000">
    <title lang="zh">SuperKitties</title>
    <desc>The SuperKitties teach Zsa-Zsa that if she takes care of planted seeds, they'll grow into fruits and veggies for everyone to enjoy.</desc>
    <date>2025-05-29</date>
  </programme>
  <programme channel="403674" start="20250529214500 +0000" stop="20250529221500 +0000">
    <title lang="zh">Bluey</title>
  <icon src="https://cdn-images.dzcdn.net/images/artist/738bd26f2c031830bcddbe883411fcca/1900x1900-000000-80-0-0.jpg"/>
  <category lang="en">Series</category>
  <category lang="en">Animation</category>
  <category lang="en">Comedy</category>
  <category lang="en">Drama</category>
  <category lang="en">Kids</category>
    <desc>Bluey plays a game of "Shops" with her friends; a pool trip is a blast, until Dad forgets everything; the Heeler family plays a game and goes on an adventure.</desc>
    <date>2025-05-29</date>
  </programme>
  <programme channel="403674" start="20250529221500 +0000" stop="20250529224000 +0000">
    <title lang="zh">Bluey</title>
  <icon src="https://cdn-images.dzcdn.net/images/artist/738bd26f2c031830bcddbe883411fcca/1900x1900-000000-80-0-0.jpg"/>
  <category lang="en">Series</category>
  <category lang="en">Animation</category>
  <category lang="en">Comedy</category>
  <category lang="en">Drama</category>
  <category lang="en">Kids</category>
    <desc>The girls convince Mum that Dad is a Big Teaser; Bluey struggles to train her new pet; Daddy Robot helps Bluey and Bingo tidy the playroom.</desc>
    <date>2025-05-29</date>
  </programme>
  <programme channel="403674" start="20250529224000 +0000" stop="20250529230500 +0000">
    <title lang="zh">Marvel's Spidey and His Amazing Friends</title>
    <desc>Zola shrinks the city's cars and Detective Stacy; Rhino mistakes Wasp for the Tooth Fairy.</desc>
    <date>2025-05-29</date>
  </programme>
  <programme channel="403674" start="20250529230500 +0000" stop="20250529233000 +0000">
    <title lang="zh">Robogobo</title>
    <desc>On Father's Day, Dax reunites a lost baby elephant with her dad while waiting to spend time with his own dad; Booster struggles with giving away his old blankie.</desc>
    <date>2025-05-29</date>
  </programme>
  <programme channel="403674" start="20250529233000 +0000" stop="20250529235500 +0000">
    <title lang="zh">Marvel's Spidey and His Amazing Friends</title>
    <desc>Lizard's monster plant takes over the city; Doc Ock captures the Spider CRAWL-R while on a mission in Space, so Miles and his mom, Rio, work together to free their ship.</desc>
    <date>2025-05-29</date>
  </programme>
  <programme channel="403674" start="20250529235500 +0000" stop="20250530000000 +0000">
    <title lang="zh">Bluey</title>
  <icon src="https://cdn-images.dzcdn.net/images/artist/738bd26f2c031830bcddbe883411fcca/1900x1900-000000-80-0-0.jpg"/>
  <category lang="en">Series</category>
  <category lang="en">Animation</category>
  <category lang="en">Comedy</category>
  <category lang="en">Drama</category>
  <category lang="en">Kids</category>
    <desc>The Heelers go on a road trip! Mum bans the girls from saying the word 'dunny.' Bluey wants to help Dad make Bingo's birthday cake.</desc>
    <date>2025-05-29</date>
  </programme>
</tv>
